{"name":"surf_ambient_njv","lightmapUrl":"https://raw.githubusercontent.com/RSCSurf/SurfMaps0/main/maps/surf_ambient_njv/lightmap.json?v=2047-7853","leafPages":[{"first":0,"count":2267,"url":"https://raw.githubusercontent.com/RSCSurf/SurfMaps0/main/maps/surf_ambient_njv/geom/leafpage0.json?v=2047-7853"}],"dispPages":[{"first":0,"count":0,"url":"https://raw.githubusercontent.com/RSCSurf/SurfMaps0/main/maps/surf_ambient_njv/geom/disppage0.json?v=2047-7853"}],"materialPages":[{"first":0,"count":22,"url":"https://raw.githubusercontent.com/RSCSurf/SurfMaps0/main/maps/surf_ambient_njv/materials/matpage0.json?v=2047-7853"}],"brushModelPages":[{"first":0,"count":1,"url":"https://raw.githubusercontent.com/RSCSurf/SurfMaps0/main/maps/surf_ambient_njv/geom/bsppage0.json?v=2047-7853"},{"first":1,"count":58,"url":"https://raw.githubusercontent.com/RSCSurf/SurfMaps0/main/maps/surf_ambient_njv/geom/bsppage1.json?v=2047-7853"}],"studioModelPages":[{"first":0,"count":0,"url":"https://raw.githubusercontent.com/RSCSurf/SurfMaps0/main/maps/surf_ambient_njv/geom/mdlpage0.json?v=2047-7853"}],"vertLightingPages":[{"first":0,"count":0,"url":"https://raw.githubusercontent.com/RSCSurf/SurfMaps0/main/maps/surf_ambient_njv/geom/vhvpage0.json?v=2047-7853"}],"visPages":[{"first":0,"count":682,"url":"https://raw.githubusercontent.com/RSCSurf/SurfMaps0/main/maps/surf_ambient_njv/geom/vispage0.json?v=2047-7853"}],"ambientPages":[{"first":0,"count":2267,"url":"https://raw.githubusercontent.com/RSCSurf/SurfMaps0/main/maps/surf_ambient_njv/geom/ambientpage0.json?v=2047-7853"}],"entities":[{"skyMaterial":{"shader":"SourceUtils.Shaders.Sky","properties":[{"name":"cullFace","type":1,"value":false},{"name":"facePosX","type":4,"value":"https://raw.githubusercontent.com/RSCSurf/SurfMaps0/main/maps/surf_ambient_njv/materials/skybox/militiart.vtf.json?v=2047-7853"},{"name":"faceNegX","type":4,"value":"https://raw.githubusercontent.com/RSCSurf/SurfMaps0/main/maps/surf_ambient_njv/materials/skybox/militialf.vtf.json?v=2047-7853"},{"name":"facePosY","type":4,"value":"https://raw.githubusercontent.com/RSCSurf/SurfMaps0/main/maps/surf_ambient_njv/materials/skybox/militiabk.vtf.json?v=2047-7853"},{"name":"faceNegY","type":4,"value":"https://raw.githubusercontent.com/RSCSurf/SurfMaps0/main/maps/surf_ambient_njv/materials/skybox/militiaft.vtf.json?v=2047-7853"},{"name":"facePosZ","type":4,"value":"https://raw.githubusercontent.com/RSCSurf/SurfMaps0/main/maps/surf_ambient_njv/materials/skybox/militiaup.vtf.json?v=2047-7853"},{"name":"faceNegZ","type":4,"value":"https://raw.githubusercontent.com/RSCSurf/SurfMaps0/main/maps/surf_ambient_njv/materials/skybox/militiadn.vtf.json?v=2047-7853"}]},"model":0,"classname":"worldspawn"},{"model":1,"clusters":[112,115,118,138,142,146],"classname":"func_brush","origin":{"x":-7459.0,"y":9113.5,"z":-7103.13}},{"classname":"water_lod_control","origin":{"x":-7459.0,"y":10309.0,"z":-6968.25}},{"classname":"light","origin":{"x":-7504.4,"y":-6631.0,"z":-7074.0}},{"classname":"light","origin":{"x":-7504.4,"y":-7983.0,"z":-7035.0}},{"classname":"light","origin":{"x":-7504.4,"y":-5395.0,"z":-7122.0}},{"classname":"light","origin":{"x":-7504.4,"y":-4742.0,"z":-7158.0}},{"classname":"light","origin":{"x":-7613.0,"y":-1865.0,"z":-8205.0}},{"classname":"light","origin":{"x":-7504.4,"y":4897.0,"z":-6688.0}},{"classname":"light","origin":{"x":-7504.4,"y":6765.0,"z":-6683.0}},{"classname":"light","origin":{"x":-7504.4,"y":7993.0,"z":-6548.0}},{"classname":"light","origin":{"x":-7504.4,"y":7778.0,"z":-6613.0}},{"classname":"light","origin":{"x":-7632.0,"y":9040.0,"z":-6638.0}},{"classname":"light","origin":{"x":-7193.0,"y":10466.0,"z":-6646.0}},{"classname":"light","origin":{"x":-7504.4,"y":11755.0,"z":-6265.0}},{"classname":"light","origin":{"x":-7504.4,"y":11922.0,"z":-4765.0}},{"classname":"light","origin":{"x":-7504.4,"y":10796.0,"z":-4250.0}},{"classname":"light","origin":{"x":-7888.0,"y":8500.0,"z":-4229.0}},{"classname":"light","origin":{"x":-7504.4,"y":4174.0,"z":-3008.0}},{"classname":"light","origin":{"x":-7504.4,"y":2758.0,"z":-3022.0}},{"classname":"light","origin":{"x":-6008.0,"y":2758.0,"z":-3072.0}},{"classname":"light","origin":{"x":-3098.0,"y":2758.0,"z":-2499.0}},{"classname":"light","origin":{"x":-768.0,"y":2758.0,"z":-2411.0}},{"classname":"light","origin":{"x":-768.0,"y":-1346.0,"z":-2318.0}},{"classname":"light","origin":{"x":-768.0,"y":-3386.0,"z":-842.0}},{"classname":"light","origin":{"x":-768.0,"y":-3076.0,"z":-1738.0}},{"classname":"light","origin":{"x":-768.0,"y":-3394.0,"z":253.0}},{"classname":"light","origin":{"x":-768.0,"y":-2242.0,"z":321.0}},{"classname":"light","origin":{"x":-768.0,"y":-700.0,"z":381.0}},{"classname":"light","origin":{"x":-768.0,"y":4110.0,"z":361.0}},{"classname":"light","origin":{"x":-768.0,"y":3156.0,"z":358.0}},{"classname":"light","origin":{"x":-768.0,"y":2335.0,"z":525.0}},{"classname":"light","origin":{"x":-768.0,"y":1068.0,"z":751.0}},{"classname":"light","origin":{"x":-768.0,"y":-64.0,"z":567.0}},{"classname":"light","origin":{"x":-768.0,"y":-1470.0,"z":338.0}},{"classname":"light","origin":{"x":-7504.4,"y":10073.0,"z":-4103.0}},{"classname":"light","origin":{"x":-7504.4,"y":11626.0,"z":-4097.0}},{"classname":"light","origin":{"x":-7504.4,"y":5377.0,"z":-3200.0}},{"classname":"light","origin":{"x":-7504.4,"y":6714.0,"z":-3962.0}},{"classname":"light","origin":{"x":-7504.4,"y":7835.0,"z":-4446.0}},{"classname":"light","origin":{"x":-7504.4,"y":3473.0,"z":-2954.0}},{"model":2,"clusters":[167,210,211],"classname":"func_brush","origin":{"x":-1088.0,"y":4140.5,"z":241.5}},{"model":3,"clusters":[161,180,194,195],"classname":"func_brush","origin":{"x":-448.0,"y":4140.5,"z":241.5}},{"classname":"trigger_push","origin":{"x":-1088.0,"y":4147.0,"z":242.0}},{"classname":"trigger_teleport","origin":{"x":-768.0,"y":3695.0,"z":65.5}},{"classname":"trigger_teleport","origin":{"x":-768.0,"y":2351.0,"z":189.5}},{"model":7,"clusters":[163,164],"classname":"func_brush","origin":{"x":-768.0,"y":4512.5,"z":243.0}},{"targetname":"Spawn1","classname":"info_teleport_destination","origin":{"x":-768.0,"y":4584.0,"z":343.0},"angles":{"x":0.0,"y":270.0,"z":0.0}},{"classname":"light","origin":{"x":-1132.0,"y":1483.0,"z":-2411.0}},{"classname":"light","origin":{"x":-377.0,"y":1432.0,"z":-2411.0}},{"classname":"light","origin":{"x":-772.0,"y":229.0,"z":-2411.0}},{"classname":"trigger_push","origin":{"x":-7457.5,"y":3551.5,"z":-7310.5}},{"model":9,"clusters":[307],"classname":"func_brush","origin":{"x":-7619.0,"y":3542.5,"z":-7317.5}},{"model":10,"clusters":[307],"classname":"func_brush","origin":{"x":-7299.0,"y":3541.5,"z":-7317.5}},{"classname":"trigger_teleport","origin":{"x":-7455.5,"y":-8651.0,"z":-6938.5}},{"classname":"light","origin":{"x":-1153.0,"y":4423.0,"z":361.0}},{"classname":"light","origin":{"x":-766.0,"y":4429.0,"z":361.0}},{"classname":"light","origin":{"x":-330.0,"y":4446.0,"z":361.0}},{"classname":"light","origin":{"x":-1170.0,"y":3977.0,"z":361.0}},{"classname":"light","origin":{"x":-427.0,"y":3969.0,"z":361.0}},{"classname":"light","origin":{"x":-1081.0,"y":4178.0,"z":361.0}},{"classname":"light","origin":{"x":-450.0,"y":4182.0,"z":361.0}},{"classname":"light","origin":{"x":-760.0,"y":4170.0,"z":361.0}},{"classname":"light","origin":{"x":-7462.0,"y":-9871.0,"z":-7125.0}},{"classname":"light","origin":{"x":-7462.0,"y":-10658.0,"z":-7268.0}},{"classname":"light","origin":{"x":-7462.0,"y":-11954.0,"z":-7506.0}},{"classname":"light","origin":{"x":-7462.0,"y":-9071.0,"z":-6822.0}},{"classname":"light","origin":{"x":-7462.0,"y":-8248.0,"z":-6825.0}},{"classname":"light","origin":{"x":-369.0,"y":3076.0,"z":361.0}},{"classname":"light","origin":{"x":-1155.0,"y":3092.0,"z":361.0}},{"classname":"light","origin":{"x":-761.0,"y":2568.0,"z":361.0}},{"classname":"light","origin":{"x":-1132.0,"y":2112.0,"z":-2411.0}},{"classname":"light","origin":{"x":-1116.0,"y":989.0,"z":-2411.0}},{"classname":"light","origin":{"x":-2268.0,"y":3166.0,"z":-2411.0}},{"classname":"light","origin":{"x":-2300.0,"y":2372.0,"z":-2411.0}},{"classname":"light","origin":{"x":-2685.0,"y":2749.0,"z":-2411.0}},{"classname":"light","origin":{"x":-5242.0,"y":2776.0,"z":-2987.0}},{"classname":"light","origin":{"x":-6039.0,"y":3197.0,"z":-2987.0}},{"classname":"light","origin":{"x":-6066.0,"y":2395.0,"z":-2987.0}},{"classname":"light","origin":{"x":-7534.0,"y":2842.0,"z":-2987.0}},{"classname":"light","origin":{"x":-7045.0,"y":3841.0,"z":-3078.0}},{"classname":"light","origin":{"x":-7815.0,"y":3921.0,"z":-3078.0}},{"classname":"light","origin":{"x":-7855.0,"y":5558.0,"z":-3078.0}},{"classname":"light","origin":{"x":-7086.0,"y":5558.0,"z":-3078.0}},{"classname":"light","origin":{"x":-7838.0,"y":11873.0,"z":-4097.0}},{"classname":"light","origin":{"x":-7104.0,"y":11841.0,"z":-4097.0}},{"classname":"light","origin":{"x":-7104.0,"y":11848.0,"z":-5486.0}},{"classname":"light","origin":{"x":-7838.0,"y":11880.0,"z":-5486.0}},{"classname":"light","origin":{"x":-7104.0,"y":11580.0,"z":-6080.0}},{"classname":"light","origin":{"x":-7838.0,"y":11612.0,"z":-6080.0}},{"classname":"light","origin":{"x":-7104.0,"y":11250.0,"z":-6663.0}},{"classname":"light","origin":{"x":-7838.0,"y":11282.0,"z":-6663.0}},{"classname":"light","origin":{"x":-7104.0,"y":9608.0,"z":-6864.0}},{"classname":"light","origin":{"x":-7838.0,"y":9640.0,"z":-6864.0}},{"classname":"light","origin":{"x":-7832.0,"y":5234.0,"z":-6688.0}},{"classname":"light","origin":{"x":-7050.0,"y":5242.0,"z":-6688.0}},{"classname":"light","origin":{"x":-7066.0,"y":6092.0,"z":-6688.0}},{"classname":"light","origin":{"x":-7848.0,"y":6084.0,"z":-6688.0}},{"classname":"light","origin":{"x":-7106.0,"y":6886.0,"z":-6688.0}},{"classname":"light","origin":{"x":-7888.0,"y":6878.0,"z":-6688.0}},{"classname":"light","origin":{"x":-7078.0,"y":7415.0,"z":-6688.0}},{"classname":"light","origin":{"x":-7860.0,"y":7407.0,"z":-6688.0}},{"classname":"light","origin":{"x":-7504.4,"y":6414.0,"z":-7046.0}},{"classname":"light","origin":{"x":-7504.4,"y":6353.0,"z":-6464.0}},{"classname":"light","origin":{"x":-7504.4,"y":4882.0,"z":-6417.0}},{"classname":"light","origin":{"x":-7504.4,"y":7350.0,"z":-6419.0}},{"classname":"light","origin":{"x":-7881.0,"y":-9436.0,"z":-7125.0}},{"classname":"light","origin":{"x":-7069.0,"y":-9455.0,"z":-7125.0}},{"classname":"light","origin":{"x":-7022.0,"y":-10097.0,"z":-7125.0}},{"classname":"light","origin":{"x":-7834.0,"y":-10078.0,"z":-7125.0}},{"classname":"light","origin":{"x":-7042.0,"y":-11240.0,"z":-7125.0}},{"classname":"light","origin":{"x":-7854.0,"y":-11221.0,"z":-7125.0}},{"classname":"light","origin":{"x":-7042.0,"y":-11695.0,"z":-7125.0}},{"classname":"light","origin":{"x":-7854.0,"y":-11676.0,"z":-7125.0}},{"classname":"light","origin":{"x":-7455.0,"y":-12100.0,"z":-7166.0}},{"classname":"trigger_teleport","origin":{"x":-7464.82,"y":-12171.0,"z":-7284.27}},{"classname":"light","origin":{"x":-7536.88,"y":-12618.0,"z":-10993.0}},{"classname":"light","origin":{"x":-7536.88,"y":-12637.0,"z":-10739.0}},{"classname":"light","origin":{"x":-7536.88,"y":-12642.0,"z":-10385.0}},{"classname":"light","origin":{"x":-7536.88,"y":-12632.0,"z":-9928.0}},{"classname":"light","origin":{"x":-7536.88,"y":-12620.0,"z":-10168.0}},{"classname":"light","origin":{"x":-7536.88,"y":-12795.0,"z":-9442.0}},{"classname":"light","origin":{"x":-7536.88,"y":-12411.0,"z":-9116.0}},{"classname":"light","origin":{"x":-7536.88,"y":-12750.0,"z":-9057.0}},{"classname":"light","origin":{"x":-7536.88,"y":-12817.0,"z":-8688.0}},{"classname":"light","origin":{"x":-7536.88,"y":-12365.0,"z":-8221.0}},{"classname":"light","origin":{"x":-7536.88,"y":-12733.0,"z":-8147.0}},{"classname":"light","origin":{"x":-7471.0,"y":-12795.0,"z":-7660.0}},{"classname":"light","origin":{"x":-7844.0,"y":-12374.0,"z":-7271.0}},{"classname":"light","origin":{"x":-7476.0,"y":-12837.0,"z":-7280.0}},{"classname":"water_lod_control","origin":{"x":-7457.0,"y":-12554.4,"z":-11141.0}},{"classname":"water_lod_control","origin":{"x":-7854.0,"y":-13037.9,"z":-11625.0}},{"classname":"trigger_teleport","origin":{"x":-7459.0,"y":-12622.0,"z":-11269.5}},{"classname":"trigger_teleport","origin":{"x":-7459.0,"y":-12622.0,"z":-10422.5}},{"classname":"trigger_teleport","origin":{"x":-7459.0,"y":-12607.0,"z":-11577.0}},{"classname":"trigger_teleport","origin":{"x":-7459.0,"y":-12623.0,"z":-10849.0}},{"model":17,"clusters":[661,662,668],"classname":"func_brush","origin":{"x":-7460.5,"y":-12612.5,"z":-11546.0}},{"classname":"light","origin":{"x":-7444.3,"y":-12960.0,"z":-11549.0}},{"classname":"light","origin":{"x":-7444.3,"y":-12616.0,"z":-11395.0}},{"classname":"light","origin":{"x":-7444.3,"y":-12277.0,"z":-11535.0}},{"classname":"light","origin":{"x":-7916.0,"y":-12629.0,"z":-11535.0}},{"classname":"light","origin":{"x":-7008.0,"y":-12641.0,"z":-11535.0}},{"classname":"light","origin":{"x":-7459.0,"y":-12508.0,"z":-11637.0}},{"classname":"light","origin":{"x":-7827.0,"y":10073.0,"z":-4386.0}},{"classname":"light","origin":{"x":-7085.0,"y":10073.0,"z":-4414.0}},{"classname":"light","origin":{"x":-7221.0,"y":10073.0,"z":-4072.0}},{"classname":"light","origin":{"x":-7740.0,"y":10073.0,"z":-4078.0}},{"classname":"light","origin":{"x":-7707.0,"y":10916.0,"z":-4078.0}},{"classname":"light","origin":{"x":-7219.0,"y":10863.0,"z":-4078.0}},{"classname":"light","origin":{"x":-7840.0,"y":8719.0,"z":-4078.0}},{"classname":"light","origin":{"x":-7077.0,"y":8673.0,"z":-4078.0}},{"classname":"light","origin":{"x":-1132.0,"y":2109.0,"z":-2570.0}},{"classname":"light","origin":{"x":-1154.0,"y":1669.0,"z":-2570.0}},{"classname":"light","origin":{"x":-340.0,"y":2479.0,"z":-2570.0}},{"classname":"light","origin":{"x":-815.0,"y":2486.0,"z":-2570.0}},{"classname":"light","origin":{"x":-1141.0,"y":607.0,"z":-2411.0}},{"classname":"light","origin":{"x":-489.0,"y":592.0,"z":-2411.0}},{"classname":"trigger_teleport","origin":{"x":-7459.0,"y":-13660.5,"z":-9731.0}},{"classname":"trigger_teleport","origin":{"x":-7459.0,"y":-12856.5,"z":-8533.5}},{"classname":"light","origin":{"x":-7198.62,"y":-13912.0,"z":-9543.0}},{"classname":"light","origin":{"x":-7198.62,"y":-13191.0,"z":-9455.0}},{"classname":"light","origin":{"x":-7198.62,"y":-13214.0,"z":-8472.0}},{"classname":"light","origin":{"x":-7198.62,"y":-13199.0,"z":-8714.0}},{"classname":"water_lod_control","origin":{"x":-777.219,"y":4559.0,"z":270.0}},{"classname":"light","origin":{"x":-1178.0,"y":-1064.0,"z":338.0}},{"classname":"light","origin":{"x":-1178.0,"y":-1836.0,"z":321.0}},{"classname":"light","origin":{"x":-381.0,"y":-1474.0,"z":338.0}},{"classname":"light","origin":{"x":-381.0,"y":-2246.0,"z":321.0}},{"classname":"light","origin":{"x":-768.0,"y":-3468.0,"z":-261.0}},{"classname":"light","origin":{"x":-768.0,"y":-2833.0,"z":-2555.0}},{"classname":"light","origin":{"x":-768.0,"y":-2480.0,"z":-2030.0}},{"classname":"light","origin":{"x":-768.0,"y":-1568.0,"z":-2313.0}},{"classname":"light","origin":{"x":-768.0,"y":-531.0,"z":-2534.0}},{"classname":"light","origin":{"x":-768.0,"y":63.0,"z":-2674.0}},{"classname":"light","origin":{"x":-768.0,"y":-534.0,"z":-2255.0}},{"classname":"light","origin":{"x":-768.0,"y":-1606.0,"z":-2131.0}},{"classname":"light","origin":{"x":-768.0,"y":-3792.0,"z":-1466.0}},{"classname":"trigger_teleport","origin":{"x":-7460.0,"y":-13059.0,"z":-8763.5}},{"classname":"trigger_teleport","origin":{"x":-7460.0,"y":-13059.0,"z":-9486.5}},{"classname":"func_water_analog","origin":{"x":-768.0,"y":4559.5,"z":243.0}},{"classname":"light","origin":{"x":-767.367,"y":3515.0,"z":651.0}},{"classname":"trigger_teleport","origin":{"x":-7459.0,"y":-12851.5,"z":-9713.0}},{"classname":"prop_ragdoll","origin":{"x":-542.0,"y":3758.0,"z":2075.0},"angles":{"x":-90.0,"y":308.0,"z":0.0}},{"classname":"prop_ragdoll","origin":{"x":-803.0,"y":3675.0,"z":2075.0},"angles":{"x":-90.0,"y":261.5,"z":0.0}},{"classname":"prop_ragdoll","origin":{"x":-1042.0,"y":3807.0,"z":2075.0},"angles":{"x":-90.0,"y":216.5,"z":0.0}},{"classname":"prop_ragdoll","origin":{"x":-1124.0,"y":4068.0,"z":2075.0},"angles":{"x":-90.0,"y":173.5,"z":0.0}},{"classname":"prop_ragdoll","origin":{"x":-731.0,"y":4386.0,"z":2075.0},"angles":{"x":-90.0,"y":83.5,"z":0.0}},{"classname":"prop_ragdoll","origin":{"x":-495.0,"y":4254.0,"z":2075.0},"angles":{"x":-90.0,"y":39.5,"z":0.0}},{"classname":"prop_ragdoll","origin":{"x":-414.0,"y":3996.0,"z":2075.0},"angles":{"x":-90.0,"y":353.5,"z":0.0}},{"classname":"light","origin":{"x":-449.0,"y":3998.0,"z":2158.0}},{"classname":"light","origin":{"x":-563.0,"y":3785.0,"z":2158.0}},{"classname":"light","origin":{"x":-798.0,"y":3711.0,"z":2158.0}},{"classname":"light","origin":{"x":-1015.0,"y":3827.0,"z":2158.0}},{"classname":"light","origin":{"x":-1089.0,"y":4065.0,"z":2158.0}},{"classname":"light","origin":{"x":-975.0,"y":4282.0,"z":2158.0}},{"classname":"light","origin":{"x":-735.0,"y":4353.0,"z":2158.0}},{"classname":"light","origin":{"x":-523.0,"y":4233.0,"z":2158.0}},{"classname":"trigger_once","origin":{"x":-775.0,"y":4031.0,"z":2110.0}},{"targetname":"rotating","classname":"func_rotating","origin":{"x":-767.0,"y":4031.0,"z":2313.0},"angles":{"x":0.0,"y":0.0,"z":0.0}},{"model":26,"clusters":[159,175,176],"targetname":"spawndoor1","classname":"func_brush","origin":{"x":-829.0,"y":4031.0,"z":1999.0}},{"model":27,"clusters":[159,175,176],"targetname":"spawndoor2","classname":"func_brush","origin":{"x":-705.0,"y":4031.0,"z":1999.0}},{"classname":"env_lightglow","origin":{"x":-767.0,"y":4031.0,"z":1238.0},"angles":{"x":-90.0,"y":0.0,"z":0.0}},{"classname":"env_lightglow","origin":{"x":-807.0,"y":3959.0,"z":1238.0},"angles":{"x":-90.0,"y":0.0,"z":0.0}},{"classname":"env_lightglow","origin":{"x":-767.0,"y":4111.0,"z":1238.0},"angles":{"x":-90.0,"y":0.0,"z":0.0}},{"classname":"env_lightglow","origin":{"x":-871.0,"y":4031.0,"z":1238.0},"angles":{"x":-90.0,"y":0.0,"z":0.0}},{"classname":"env_lightglow","origin":{"x":-839.0,"y":3983.0,"z":1238.0},"angles":{"x":-90.0,"y":0.0,"z":0.0}},{"classname":"env_lightglow","origin":{"x":-823.0,"y":4095.0,"z":1238.0},"angles":{"x":-90.0,"y":0.0,"z":0.0}},{"classname":"env_lightglow","origin":{"x":-767.0,"y":3943.0,"z":1238.0},"angles":{"x":-90.0,"y":0.0,"z":0.0}},{"classname":"env_lightglow","origin":{"x":-726.0,"y":3977.0,"z":1238.0},"angles":{"x":-90.0,"y":0.0,"z":0.0}},{"classname":"env_lightglow","origin":{"x":-696.0,"y":3982.0,"z":1238.0},"angles":{"x":-90.0,"y":0.0,"z":0.0}},{"classname":"env_lightglow","origin":{"x":-679.0,"y":4031.0,"z":1238.0},"angles":{"x":-90.0,"y":0.0,"z":0.0}},{"classname":"env_lightglow","origin":{"x":-716.0,"y":4109.0,"z":1238.0},"angles":{"x":-90.0,"y":0.0,"z":0.0}},{"classname":"env_lightglow","origin":{"x":-807.0,"y":4055.0,"z":1238.0},"angles":{"x":-90.0,"y":0.0,"z":0.0}},{"classname":"env_lightglow","origin":{"x":-805.0,"y":4004.0,"z":1238.0},"angles":{"x":-90.0,"y":0.0,"z":0.0}},{"classname":"env_lightglow","origin":{"x":-751.0,"y":3991.0,"z":1238.0},"angles":{"x":-90.0,"y":0.0,"z":0.0}},{"classname":"env_lightglow","origin":{"x":-719.0,"y":4039.0,"z":1238.0},"angles":{"x":-90.0,"y":0.0,"z":0.0}},{"classname":"env_lightglow","origin":{"x":-751.0,"y":4071.0,"z":1238.0},"angles":{"x":-90.0,"y":0.0,"z":0.0}},{"classname":"trigger_teleport","origin":{"x":-767.0,"y":4032.5,"z":1457.5}},{"classname":"info_player_terrorist","origin":{"x":-784.57,"y":3480.3,"z":2012.0},"angles":{"x":0.0,"y":85.5,"z":0.0}},{"classname":"info_player_terrorist","origin":{"x":-678.0,"y":3493.0,"z":2012.0},"angles":{"x":0.0,"y":104.5,"z":0.0}},{"classname":"info_player_terrorist","origin":{"x":-626.0,"y":3504.0,"z":2012.0},"angles":{"x":0.0,"y":113.0,"z":0.0}},{"classname":"info_player_terrorist","origin":{"x":-564.186,"y":3523.89,"z":2012.0},"angles":{"x":0.0,"y":113.0,"z":0.0}},{"classname":"info_player_terrorist","origin":{"x":-514.183,"y":3548.75,"z":2012.0},"angles":{"x":0.0,"y":115.0,"z":0.0}},{"classname":"info_player_terrorist","origin":{"x":-457.805,"y":3586.9,"z":2012.0},"angles":{"x":0.0,"y":128.0,"z":0.0}},{"classname":"info_player_terrorist","origin":{"x":-401.173,"y":3627.6,"z":2012.0},"angles":{"x":0.0,"y":126.0,"z":0.0}},{"classname":"info_player_terrorist","origin":{"x":-340.0,"y":3699.0,"z":2012.0},"angles":{"x":0.0,"y":128.0,"z":0.0}},{"classname":"info_player_terrorist","origin":{"x":-286.0,"y":3792.0,"z":2012.0},"angles":{"x":0.0,"y":134.0,"z":0.0}},{"classname":"info_player_terrorist","origin":{"x":-238.0,"y":3893.0,"z":2012.0},"angles":{"x":0.0,"y":142.0,"z":0.0}},{"classname":"info_player_terrorist","origin":{"x":-218.935,"y":3973.77,"z":2012.0},"angles":{"x":0.0,"y":173.0,"z":0.0}},{"classname":"info_player_terrorist","origin":{"x":-220.602,"y":4079.66,"z":2012.0},"angles":{"x":0.0,"y":179.0,"z":0.0}},{"classname":"info_player_terrorist","origin":{"x":-247.672,"y":4186.24,"z":2012.0},"angles":{"x":0.0,"y":195.5,"z":0.0}},{"classname":"info_player_terrorist","origin":{"x":-304.539,"y":4300.81,"z":2012.0},"angles":{"x":0.0,"y":206.5,"z":0.0}},{"classname":"info_player_terrorist","origin":{"x":-390.84,"y":4412.78,"z":2012.0},"angles":{"x":0.0,"y":220.0,"z":0.0}},{"classname":"info_player_terrorist","origin":{"x":-497.0,"y":4509.0,"z":2012.0},"angles":{"x":0.0,"y":233.0,"z":0.0}},{"classname":"info_player_terrorist","origin":{"x":-592.0,"y":4548.0,"z":2012.0},"angles":{"x":0.0,"y":241.0,"z":0.0}},{"classname":"info_player_terrorist","origin":{"x":-542.0,"y":4527.0,"z":2012.0},"angles":{"x":0.0,"y":240.5,"z":0.0}},{"classname":"info_player_terrorist","origin":{"x":-424.0,"y":4454.0,"z":2012.0},"angles":{"x":0.0,"y":232.5,"z":0.0}},{"classname":"info_player_terrorist","origin":{"x":-345.24,"y":4363.02,"z":2012.0},"angles":{"x":0.0,"y":216.0,"z":0.0}},{"classname":"info_player_terrorist","origin":{"x":-272.201,"y":4239.19,"z":2012.0},"angles":{"x":0.0,"y":200.0,"z":0.0}},{"classname":"info_player_terrorist","origin":{"x":-230.07,"y":4128.87,"z":2012.0},"angles":{"x":0.0,"y":196.0,"z":0.0}},{"classname":"info_player_terrorist","origin":{"x":-219.633,"y":4027.75,"z":2012.0},"angles":{"x":0.0,"y":176.5,"z":0.0}},{"classname":"info_player_terrorist","origin":{"x":-263.0,"y":3842.0,"z":2012.0},"angles":{"x":0.0,"y":140.0,"z":0.0}},{"classname":"info_player_terrorist","origin":{"x":-311.0,"y":3742.0,"z":2012.0},"angles":{"x":0.0,"y":130.5,"z":0.0}},{"classname":"info_player_terrorist","origin":{"x":-369.537,"y":3660.86,"z":2012.0},"angles":{"x":0.0,"y":122.0,"z":0.0}},{"classname":"info_player_terrorist","origin":{"x":-732.0,"y":3483.0,"z":2012.0},"angles":{"x":0.0,"y":95.5,"z":0.0}},{"classname":"info_player_terrorist","origin":{"x":-832.945,"y":3491.03,"z":2012.0},"angles":{"x":0.0,"y":64.0,"z":0.0}},{"classname":"info_player_terrorist","origin":{"x":-906.434,"y":3505.91,"z":2012.0},"angles":{"x":0.0,"y":60.5,"z":0.0}},{"classname":"info_player_terrorist","origin":{"x":-996.328,"y":3540.58,"z":2012.0},"angles":{"x":0.0,"y":60.5,"z":0.0}},{"classname":"info_player_terrorist","origin":{"x":-1044.0,"y":3563.0,"z":2012.0},"angles":{"x":0.0,"y":42.0,"z":0.0}},{"classname":"info_player_counterterrorist","origin":{"x":-1117.0,"y":3633.0,"z":2012.0},"angles":{"x":0.0,"y":20.0,"z":0.0}},{"classname":"info_player_counterterrorist","origin":{"x":-1180.0,"y":3695.0,"z":2012.0},"angles":{"x":0.0,"y":23.5,"z":0.0}},{"classname":"info_player_counterterrorist","origin":{"x":-1215.0,"y":3740.0,"z":2012.0},"angles":{"x":0.0,"y":31.5,"z":0.0}},{"classname":"info_player_counterterrorist","origin":{"x":-1249.0,"y":3786.0,"z":2012.0},"angles":{"x":0.0,"y":26.5,"z":0.0}},{"classname":"info_player_counterterrorist","origin":{"x":-1283.0,"y":3834.0,"z":2012.0},"angles":{"x":0.0,"y":27.5,"z":0.0}},{"classname":"info_player_counterterrorist","origin":{"x":-1296.0,"y":3883.0,"z":2012.0},"angles":{"x":0.0,"y":17.5,"z":0.0}},{"classname":"info_player_counterterrorist","origin":{"x":-1299.0,"y":3928.0,"z":2012.0},"angles":{"x":0.0,"y":17.5,"z":0.0}},{"classname":"info_player_counterterrorist","origin":{"x":-1293.76,"y":4151.01,"z":2012.0},"angles":{"x":0.0,"y":335.0,"z":0.0}},{"classname":"info_player_counterterrorist","origin":{"x":-1257.21,"y":4247.84,"z":2012.0},"angles":{"x":0.0,"y":323.5,"z":0.0}},{"classname":"info_player_counterterrorist","origin":{"x":-1216.1,"y":4328.77,"z":2012.0},"angles":{"x":0.0,"y":336.0,"z":0.0}},{"classname":"info_player_counterterrorist","origin":{"x":-1159.04,"y":4399.37,"z":2012.0},"angles":{"x":0.0,"y":304.0,"z":0.0}},{"classname":"info_player_counterterrorist","origin":{"x":-1095.76,"y":4463.45,"z":2012.0},"angles":{"x":0.0,"y":313.5,"z":0.0}},{"classname":"info_player_counterterrorist","origin":{"x":-1023.33,"y":4513.2,"z":2012.0},"angles":{"x":0.0,"y":302.0,"z":0.0}},{"classname":"info_player_counterterrorist","origin":{"x":-933.423,"y":4547.83,"z":2012.0},"angles":{"x":0.0,"y":283.5,"z":0.0}},{"classname":"info_player_counterterrorist","origin":{"x":-835.672,"y":4570.88,"z":2012.0},"angles":{"x":0.0,"y":276.0,"z":0.0}},{"classname":"info_player_counterterrorist","origin":{"x":-737.997,"y":4583.86,"z":2012.0},"angles":{"x":0.0,"y":265.0,"z":0.0}},{"classname":"info_player_counterterrorist","origin":{"x":-646.91,"y":4567.56,"z":2012.0},"angles":{"x":0.0,"y":246.5,"z":0.0}},{"classname":"info_player_counterterrorist","origin":{"x":-784.741,"y":4579.56,"z":2012.0},"angles":{"x":0.0,"y":272.5,"z":0.0}},{"classname":"info_player_counterterrorist","origin":{"x":-892.04,"y":4564.81,"z":2012.0},"angles":{"x":0.0,"y":276.5,"z":0.0}},{"classname":"info_player_counterterrorist","origin":{"x":-974.893,"y":4537.37,"z":2012.0},"angles":{"x":0.0,"y":310.0,"z":0.0}},{"classname":"info_player_counterterrorist","origin":{"x":-1065.33,"y":4488.49,"z":2012.0},"angles":{"x":0.0,"y":299.5,"z":0.0}},{"classname":"info_player_counterterrorist","origin":{"x":-1136.91,"y":4433.89,"z":2012.0},"angles":{"x":0.0,"y":310.5,"z":0.0}},{"classname":"info_player_counterterrorist","origin":{"x":-1188.45,"y":4369.1,"z":2012.0},"angles":{"x":0.0,"y":317.0,"z":0.0}},{"classname":"info_player_counterterrorist","origin":{"x":-1243.0,"y":4289.0,"z":2012.0},"angles":{"x":0.0,"y":334.0,"z":0.0}},{"classname":"info_player_counterterrorist","origin":{"x":-1280.0,"y":4199.0,"z":2012.0},"angles":{"x":0.0,"y":338.5,"z":0.0}},{"classname":"info_player_counterterrorist","origin":{"x":-1302.8,"y":4098.53,"z":2012.0},"angles":{"x":0.0,"y":354.5,"z":0.0}},{"classname":"info_player_counterterrorist","origin":{"x":-1087.0,"y":3596.0,"z":2012.0},"angles":{"x":0.0,"y":26.0,"z":0.0}},{"classname":"info_player_counterterrorist","origin":{"x":-1148.0,"y":3658.0,"z":2012.0},"angles":{"x":0.0,"y":14.5,"z":0.0}},{"classname":"info_player_counterterrorist","origin":{"x":-693.0,"y":4581.0,"z":2012.0},"angles":{"x":0.0,"y":248.0,"z":0.0}},{"classname":"info_player_counterterrorist","origin":{"x":-1308.0,"y":4004.0,"z":2012.0},"angles":{"x":0.0,"y":15.0,"z":0.0}},{"classname":"info_player_counterterrorist","origin":{"x":-1309.0,"y":4049.0,"z":2012.0},"angles":{"x":0.0,"y":9.5,"z":0.0}},{"classname":"info_player_counterterrorist","origin":{"x":-1317.0,"y":3963.0,"z":2012.0},"angles":{"x":0.0,"y":7.0,"z":0.0}},{"classname":"info_player_terrorist","origin":{"x":-454.0,"y":4490.0,"z":2012.0},"angles":{"x":0.0,"y":231.5,"z":0.0}},{"classname":"env_lightglow","origin":{"x":-835.0,"y":4031.0,"z":1238.0},"angles":{"x":-90.0,"y":0.0,"z":0.0}},{"classname":"env_lightglow","origin":{"x":-843.0,"y":4065.0,"z":1238.0},"angles":{"x":-90.0,"y":0.0,"z":0.0}},{"classname":"env_lightglow","origin":{"x":-783.0,"y":4082.0,"z":1238.0},"angles":{"x":-90.0,"y":0.0,"z":0.0}},{"classname":"env_lightglow","origin":{"x":-783.0,"y":3980.0,"z":1238.0},"angles":{"x":-90.0,"y":0.0,"z":0.0}},{"classname":"env_lightglow","origin":{"x":-717.0,"y":4007.0,"z":1238.0},"angles":{"x":-90.0,"y":0.0,"z":0.0}},{"classname":"env_lightglow","origin":{"x":-693.0,"y":4068.0,"z":1238.0},"angles":{"x":-90.0,"y":0.0,"z":0.0}},{"classname":"light","origin":{"x":-767.0,"y":4031.0,"z":1432.0}},{"classname":"light","origin":{"x":-767.0,"y":4031.0,"z":1659.0}},{"classname":"light","origin":{"x":-767.0,"y":4031.0,"z":1878.0}},{"classname":"func_dustmotes"},{"classname":"func_dustmotes"},{"classname":"func_dustmotes"},{"classname":"func_dustmotes"},{"classname":"func_dustmotes"},{"classname":"func_dustmotes"},{"classname":"func_dustmotes"},{"classname":"func_dustmotes"},{"targetname":"spawnsound","classname":"ambient_generic","origin":{"x":-764.0,"y":4014.4,"z":2070.0}},{"classname":"prop_ragdoll","origin":{"x":-996.0,"y":4310.0,"z":2075.0},"angles":{"x":-90.0,"y":129.0,"z":0.0}},{"classname":"trigger_teleport","origin":{"x":-7459.0,"y":11857.0,"z":-6502.79}},{"classname":"trigger_teleport","origin":{"x":-7467.0,"y":-10675.5,"z":-7727.07}},{"classname":"trigger_teleport","origin":{"x":-7449.0,"y":-12623.0,"z":-8831.5}},{"classname":"trigger_multiple","origin":{"x":-768.0,"y":4032.5,"z":1727.0}},{"targetname":"falldmgoff","classname":"filter_damage_type","origin":{"x":-767.0,"y":4031.0,"z":2290.0}},{"classname":"trigger_push","origin":{"x":-448.0,"y":4147.0,"z":242.0}},{"classname":"light","origin":{"x":-2332.0,"y":2749.0,"z":-2557.0}},{"classname":"light","origin":{"x":-4204.0,"y":2749.0,"z":-2688.0}},{"classname":"light","origin":{"x":-6499.0,"y":2749.0,"z":-3141.0}},{"classname":"light","origin":{"x":-7210.0,"y":2749.0,"z":-3147.0}},{"classname":"light","origin":{"x":-7068.0,"y":3518.0,"z":-3147.0}},{"classname":"light","origin":{"x":-7480.0,"y":4882.0,"z":-3147.0}},{"classname":"light","origin":{"x":-7125.0,"y":4913.0,"z":-3147.0}},{"classname":"light","origin":{"x":-7717.0,"y":4882.0,"z":-3147.0}},{"classname":"light","origin":{"x":-7717.0,"y":5871.0,"z":-3413.0}},{"classname":"light","origin":{"x":-7908.0,"y":6346.0,"z":-3645.0}},{"classname":"light","origin":{"x":-7717.0,"y":7122.0,"z":-3946.0}},{"classname":"light","origin":{"x":-7717.0,"y":7626.0,"z":-4144.0}},{"classname":"light","origin":{"x":-7844.0,"y":8438.0,"z":-4271.0}},{"classname":"light","origin":{"x":-7068.0,"y":8422.0,"z":-4271.0}},{"classname":"light","origin":{"x":-7047.0,"y":9358.0,"z":-4271.0}},{"classname":"light","origin":{"x":-7823.0,"y":9374.0,"z":-4271.0}},{"classname":"light","origin":{"x":-7014.0,"y":10664.0,"z":-4271.0}},{"classname":"light","origin":{"x":-7790.0,"y":10680.0,"z":-4271.0}},{"classname":"light","origin":{"x":-7049.0,"y":7118.0,"z":-3946.0}},{"classname":"light","origin":{"x":-7049.0,"y":7622.0,"z":-4144.0}},{"classname":"light","origin":{"x":-7049.0,"y":6335.0,"z":-3645.0}},{"classname":"light","origin":{"x":-7502.0,"y":6345.0,"z":-3645.0}},{"classname":"light","origin":{"x":-7428.0,"y":7246.0,"z":-3946.0}},{"classname":"light","origin":{"x":-7428.0,"y":7747.0,"z":-4165.0}},{"classname":"light","origin":{"x":-7428.0,"y":8508.0,"z":-4122.0}},{"classname":"light","origin":{"x":-7462.0,"y":9193.0,"z":-4122.0}},{"classname":"light","origin":{"x":-7459.0,"y":9696.0,"z":-4122.0}},{"classname":"light","origin":{"x":-7451.0,"y":10440.0,"z":-4122.0}},{"classname":"light","origin":{"x":-7456.0,"y":11017.0,"z":-4122.0}},{"classname":"light","origin":{"x":-7437.0,"y":11492.0,"z":-4330.0}},{"classname":"light","origin":{"x":-7437.0,"y":10453.0,"z":-4401.0}},{"classname":"light","origin":{"x":-7504.4,"y":11979.0,"z":-4046.0}},{"classname":"light","origin":{"x":-7504.4,"y":11927.0,"z":-4457.0}},{"classname":"light","origin":{"x":-7504.4,"y":11921.0,"z":-5066.0}},{"classname":"light","origin":{"x":-7504.4,"y":11067.0,"z":-6564.0}},{"classname":"light","origin":{"x":-7504.4,"y":10532.0,"z":-6492.0}},{"classname":"light","origin":{"x":-7504.4,"y":10245.0,"z":-6807.0}},{"classname":"light","origin":{"x":-7504.4,"y":9462.0,"z":-6843.0}},{"classname":"light","origin":{"x":-7801.0,"y":9793.0,"z":-6843.0}},{"classname":"light","origin":{"x":-7064.0,"y":10039.0,"z":-6843.0}},{"classname":"light","origin":{"x":-7064.0,"y":11075.0,"z":-6567.0}},{"classname":"light","origin":{"x":-7681.0,"y":10761.0,"z":-6694.0}},{"classname":"light","origin":{"x":-7237.0,"y":9038.0,"z":-6638.0}},{"classname":"light","origin":{"x":-7267.0,"y":8478.0,"z":-6638.0}},{"classname":"light","origin":{"x":-7662.0,"y":8480.0,"z":-6638.0}},{"classname":"light","origin":{"x":-7736.0,"y":5647.0,"z":-6688.0}},{"classname":"light","origin":{"x":-7088.0,"y":5631.0,"z":-6688.0}},{"classname":"light","origin":{"x":-7431.0,"y":5465.0,"z":-6688.0}},{"classname":"light","origin":{"x":-7431.0,"y":4310.0,"z":-6784.0}},{"classname":"light","origin":{"x":-7763.0,"y":4319.0,"z":-6784.0}},{"classname":"light","origin":{"x":-7027.0,"y":4286.0,"z":-6784.0}},{"classname":"light","origin":{"x":-7027.0,"y":3702.0,"z":-6936.0}},{"classname":"light","origin":{"x":-7431.0,"y":3726.0,"z":-6936.0}},{"classname":"light","origin":{"x":-7763.0,"y":3735.0,"z":-6936.0}},{"classname":"light","origin":{"x":-7027.0,"y":2884.0,"z":-7116.0}},{"classname":"light","origin":{"x":-7431.0,"y":2908.0,"z":-7116.0}},{"classname":"light","origin":{"x":-7763.0,"y":2917.0,"z":-7116.0}},{"classname":"light","origin":{"x":-7027.0,"y":1233.0,"z":-7418.0}},{"classname":"light","origin":{"x":-7431.0,"y":1257.0,"z":-7418.0}},{"classname":"light","origin":{"x":-7763.0,"y":1266.0,"z":-7418.0}},{"classname":"light","origin":{"x":-7027.0,"y":-497.0,"z":-7832.0}},{"classname":"light","origin":{"x":-7431.0,"y":-473.0,"z":-7832.0}},{"classname":"light","origin":{"x":-7763.0,"y":-464.0,"z":-7832.0}},{"classname":"light","origin":{"x":-7027.0,"y":-2132.0,"z":-8011.0}},{"classname":"light","origin":{"x":-7431.0,"y":-2108.0,"z":-8011.0}},{"classname":"light","origin":{"x":-7763.0,"y":-2099.0,"z":-8011.0}},{"classname":"light","origin":{"x":-7027.0,"y":-3418.0,"z":-7596.0}},{"classname":"light","origin":{"x":-7431.0,"y":-3394.0,"z":-7596.0}},{"classname":"light","origin":{"x":-7763.0,"y":-3385.0,"z":-7596.0}},{"classname":"light","origin":{"x":-7027.0,"y":-3932.0,"z":-7366.0}},{"classname":"light","origin":{"x":-7431.0,"y":-3908.0,"z":-7366.0}},{"classname":"light","origin":{"x":-7763.0,"y":-3899.0,"z":-7366.0}},{"classname":"light","origin":{"x":-7027.0,"y":-4504.0,"z":-7208.0}},{"classname":"light","origin":{"x":-7431.0,"y":-4480.0,"z":-7208.0}},{"classname":"light","origin":{"x":-7763.0,"y":-4471.0,"z":-7208.0}},{"classname":"light","origin":{"x":-7027.0,"y":-5273.0,"z":-6919.0}},{"classname":"light","origin":{"x":-7431.0,"y":-5249.0,"z":-6919.0}},{"classname":"light","origin":{"x":-7763.0,"y":-5240.0,"z":-6919.0}},{"classname":"light","origin":{"x":-7027.0,"y":-5905.0,"z":-6909.0}},{"classname":"light","origin":{"x":-7431.0,"y":-5881.0,"z":-6909.0}},{"classname":"light","origin":{"x":-7763.0,"y":-5872.0,"z":-6909.0}},{"classname":"trigger_teleport","origin":{"x":-7459.5,"y":7962.0,"z":-7141.5}},{"classname":"trigger_teleport","origin":{"x":-7459.5,"y":1256.0,"z":-7871.38}},{"classname":"trigger_teleport","origin":{"x":-7451.0,"y":-3608.5,"z":-8058.75}},{"classname":"trigger_teleport","origin":{"x":-7459.0,"y":-6631.5,"z":-7525.38}},{"classname":"light","origin":{"x":-7462.0,"y":-8647.0,"z":-6827.0}},{"classname":"light","origin":{"x":-7487.0,"y":-12460.0,"z":-7660.0}},{"classname":"light","origin":{"x":-7268.0,"y":-12472.0,"z":-7467.0}},{"classname":"light","origin":{"x":-7793.0,"y":-12787.0,"z":-7467.0}},{"classname":"light","origin":{"x":-7044.0,"y":-12392.0,"z":-7271.0}},{"classname":"trigger_teleport","origin":{"x":-7459.0,"y":-12864.0,"z":-7940.0}},{"classname":"trigger_teleport","origin":{"x":-7467.0,"y":-12615.0,"z":-7940.0}},{"classname":"light","origin":{"x":-7536.88,"y":-12783.0,"z":-8360.0}},{"classname":"light","origin":{"x":-7828.0,"y":-12490.0,"z":-8690.0}},{"classname":"light","origin":{"x":-7046.0,"y":-12505.0,"z":-8690.0}},{"classname":"light","origin":{"x":-7061.0,"y":-12847.0,"z":-8690.0}},{"classname":"light","origin":{"x":-7843.0,"y":-12832.0,"z":-8690.0}},{"classname":"light","origin":{"x":-7452.0,"y":-13186.0,"z":-8714.0}},{"classname":"light","origin":{"x":-7632.0,"y":-13199.0,"z":-8714.0}},{"classname":"light","origin":{"x":-7198.62,"y":-13669.0,"z":-8902.0}},{"classname":"light","origin":{"x":-7198.62,"y":-13313.0,"z":-9014.0}},{"classname":"light","origin":{"x":-7860.0,"y":-13310.0,"z":-9014.0}},{"classname":"light","origin":{"x":-7860.0,"y":-13666.0,"z":-8902.0}},{"classname":"light","origin":{"x":-7860.0,"y":-13958.0,"z":-8701.0}},{"classname":"light","origin":{"x":-7860.0,"y":-13406.0,"z":-9434.0}},{"classname":"light","origin":{"x":-7860.0,"y":-13762.0,"z":-9322.0}},{"classname":"light","origin":{"x":-7860.0,"y":-14054.0,"z":-9121.0}},{"classname":"light","origin":{"x":-7090.0,"y":-13420.0,"z":-9430.0}},{"classname":"light","origin":{"x":-7090.0,"y":-13776.0,"z":-9318.0}},{"classname":"light","origin":{"x":-7090.0,"y":-14068.0,"z":-9117.0}},{"classname":"light","origin":{"x":-7536.88,"y":-12434.0,"z":-9703.0}},{"classname":"light","origin":{"x":-7128.0,"y":-12841.0,"z":-9442.0}},{"classname":"light","origin":{"x":-7822.0,"y":-12852.0,"z":-9442.0}},{"classname":"light","origin":{"x":-7458.0,"y":-12688.0,"z":-11637.0}},{"classname":"light","origin":{"x":-7820.0,"y":-12765.0,"z":-9057.0}},{"classname":"light","origin":{"x":-7820.0,"y":-12426.0,"z":-9116.0}},{"classname":"light","origin":{"x":-7151.0,"y":-12792.0,"z":-9057.0}},{"classname":"light","origin":{"x":-7151.0,"y":-12453.0,"z":-9116.0}},{"classname":"env_lightglow","origin":{"x":-799.0,"y":4125.0,"z":1238.0},"angles":{"x":-90.0,"y":0.0,"z":0.0}},{"classname":"env_lightglow","origin":{"x":-738.0,"y":4127.0,"z":1238.0},"angles":{"x":-90.0,"y":0.0,"z":0.0}},{"classname":"env_lightglow","origin":{"x":-723.0,"y":4066.0,"z":1238.0},"angles":{"x":-90.0,"y":0.0,"z":0.0}},{"classname":"env_lightglow","origin":{"x":-791.0,"y":4032.0,"z":1238.0},"angles":{"x":-90.0,"y":0.0,"z":0.0}},{"classname":"env_lightglow","origin":{"x":-699.0,"y":3949.0,"z":1238.0},"angles":{"x":-90.0,"y":0.0,"z":0.0}},{"classname":"env_lightglow","origin":{"x":-738.0,"y":3931.0,"z":1238.0},"angles":{"x":-90.0,"y":0.0,"z":0.0}},{"classname":"env_lightglow","origin":{"x":-793.0,"y":3929.0,"z":1238.0},"angles":{"x":-90.0,"y":0.0,"z":0.0}},{"classname":"env_lightglow","origin":{"x":-661.0,"y":4004.0,"z":1238.0},"angles":{"x":-90.0,"y":0.0,"z":0.0}},{"classname":"env_lightglow","origin":{"x":-665.0,"y":4072.0,"z":1238.0},"angles":{"x":-90.0,"y":0.0,"z":0.0}},{"classname":"env_lightglow","origin":{"x":-682.0,"y":4096.0,"z":1238.0},"angles":{"x":-90.0,"y":0.0,"z":0.0}},{"classname":"env_lightglow","origin":{"x":-766.0,"y":4144.0,"z":1238.0},"angles":{"x":-90.0,"y":0.0,"z":0.0}},{"classname":"env_lightglow","origin":{"x":-851.0,"y":4097.0,"z":1238.0},"angles":{"x":-90.0,"y":0.0,"z":0.0}},{"classname":"env_lightglow","origin":{"x":-867.0,"y":4063.0,"z":1238.0},"angles":{"x":-90.0,"y":0.0,"z":0.0}},{"classname":"env_lightglow","origin":{"x":-861.0,"y":4000.0,"z":1238.0},"angles":{"x":-90.0,"y":0.0,"z":0.0}},{"classname":"env_lightglow","origin":{"x":-832.0,"y":3949.0,"z":1238.0},"angles":{"x":-90.0,"y":0.0,"z":0.0}},{"classname":"env_lightglow","origin":{"x":-859.0,"y":3970.0,"z":1238.0},"angles":{"x":-90.0,"y":0.0,"z":0.0}},{"classname":"env_lightglow","origin":{"x":-766.0,"y":3920.0,"z":1238.0},"angles":{"x":-90.0,"y":0.0,"z":0.0}},{"classname":"env_lightglow","origin":{"x":-729.0,"y":3951.0,"z":1238.0},"angles":{"x":-90.0,"y":0.0,"z":0.0}},{"classname":"env_lightglow","origin":{"x":-755.0,"y":3965.0,"z":1238.0},"angles":{"x":-90.0,"y":0.0,"z":0.0}},{"classname":"env_sun","origin":{"x":-767.0,"y":4031.0,"z":2274.0},"angles":{"x":0.0,"y":0.0,"z":0.0}},{"Brightness":{"R":255,"G":255,"B":255,"A":200},"Ambient":{"R":255,"G":255,"B":255,"A":20},"BrightnessHdr":{"R":255,"G":255,"B":255,"A":1},"AmbientHdr":{"R":255,"G":255,"B":255,"A":1},"BrightnessScaleHdr":1.0,"AmbientScaleHdr":1.0,"Pitch":-90.0,"classname":"light_environment","origin":{"x":-767.0,"y":4031.0,"z":2258.0},"angles":{"x":0.0,"y":0.0,"z":0.0}},{"classname":"light","origin":{"x":-1155.0,"y":2497.0,"z":477.0}},{"classname":"light","origin":{"x":-369.0,"y":2481.0,"z":477.0}},{"classname":"light","origin":{"x":-1155.0,"y":1922.0,"z":609.0}},{"classname":"light","origin":{"x":-369.0,"y":1906.0,"z":609.0}},{"classname":"light","origin":{"x":-1155.0,"y":1037.0,"z":559.0}},{"classname":"light","origin":{"x":-369.0,"y":1021.0,"z":559.0}},{"classname":"light","origin":{"x":-1155.0,"y":-371.0,"z":465.0}},{"classname":"light","origin":{"x":-369.0,"y":-387.0,"z":465.0}},{"classname":"light","origin":{"x":-1155.0,"y":-894.0,"z":278.0}},{"classname":"light","origin":{"x":-369.0,"y":-910.0,"z":278.0}},{"classname":"light","origin":{"x":-1155.0,"y":-2192.0,"z":38.0}},{"classname":"light","origin":{"x":-369.0,"y":-2208.0,"z":38.0}},{"classname":"light","origin":{"x":-1155.0,"y":-3001.0,"z":190.0}},{"classname":"light","origin":{"x":-369.0,"y":-3017.0,"z":190.0}},{"classname":"trigger_teleport","origin":{"x":-775.5,"y":262.5,"z":-2796.5}},{"classname":"trigger_teleport","origin":{"x":-768.0,"y":-3363.0,"z":-2128.5}},{"classname":"trigger_teleport","origin":{"x":-2264.0,"y":2761.5,"z":-2804.0}},{"classname":"trigger_teleport","origin":{"x":-4104.0,"y":2761.5,"z":-3127.5}},{"classname":"trigger_teleport","origin":{"x":-776.5,"y":-2401.0,"z":-174.5}},{"classname":"trigger_teleport","origin":{"x":-6529.5,"y":2761.0,"z":-3451.0}},{"classname":"trigger_teleport","origin":{"x":-7451.5,"y":3690.5,"z":-3451.0}},{"classname":"trigger_teleport","origin":{"x":-7451.5,"y":6532.5,"z":-4008.5}},{"classname":"trigger_teleport","origin":{"x":-7459.0,"y":9806.0,"z":-4566.0}},{"classname":"light","origin":{"x":-1553.0,"y":2742.0,"z":-2557.0}},{"classname":"light","origin":{"x":-1567.0,"y":3059.0,"z":-2557.0}},{"classname":"light","origin":{"x":-1553.0,"y":2535.0,"z":-2557.0}},{"classname":"light","origin":{"x":-987.0,"y":2842.0,"z":-2557.0}},{"classname":"info_player_start","origin":{"x":-761.0,"y":4491.0,"z":2012.0},"angles":{"x":0.0,"y":270.5,"z":0.0}},{"classname":"light","origin":{"x":-5574.0,"y":3121.0,"z":-3119.0}},{"classname":"light","origin":{"x":-4582.0,"y":3113.0,"z":-2872.0}},{"classname":"light","origin":{"x":-3739.0,"y":3113.0,"z":-2543.0}},{"classname":"light","origin":{"x":-3714.0,"y":2375.0,"z":-2543.0}},{"classname":"light","origin":{"x":-4557.0,"y":2375.0,"z":-2872.0}},{"classname":"trigger_teleport","origin":{"x":-768.0,"y":-673.0,"z":69.5}},{"classname":"trigger_teleport","origin":{"x":-768.0,"y":1055.0,"z":313.5}},{"targetname":"Spawnprot","classname":"info_teleport_destination","origin":{"x":-765.0,"y":4030.0,"z":1921.0},"angles":{"x":0.0,"y":0.0,"z":0.0}},{"classname":"light","origin":{"x":-7015.0,"y":-12441.0,"z":-11535.0}},{"classname":"light","origin":{"x":-7004.0,"y":-12846.0,"z":-11535.0}},{"classname":"light","origin":{"x":-7907.0,"y":-12842.0,"z":-11535.0}},{"classname":"light","origin":{"x":-7090.0,"y":-12959.0,"z":-11535.0}},{"classname":"light","origin":{"x":-7918.0,"y":-12934.0,"z":-11535.0}},{"classname":"light","origin":{"x":-7914.0,"y":-12435.0,"z":-11535.0}},{"classname":"light","origin":{"x":-7844.0,"y":-12278.0,"z":-11535.0}},{"classname":"light","origin":{"x":-7602.0,"y":-12273.0,"z":-11535.0}},{"classname":"light","origin":{"x":-7016.0,"y":-12298.0,"z":-11535.0}},{"classname":"light","origin":{"x":-7198.62,"y":-13961.0,"z":-8701.0}},{"classname":"game_player_equip","origin":{"x":-767.0,"y":4031.0,"z":2242.0}}]}