{"name":"surf_boy_fixed","lightmapUrl":"https://raw.githubusercontent.com/RSCSurf/SurfMaps0/main/maps/surf_boy_fixed/lightmap.json?v=2047-9d6b","leafPages":[{"first":0,"count":8192,"url":"https://raw.githubusercontent.com/RSCSurf/SurfMaps0/main/maps/surf_boy_fixed/geom/leafpage0.json?v=2047-9d6b"},{"first":8192,"count":1989,"url":"https://raw.githubusercontent.com/RSCSurf/SurfMaps0/main/maps/surf_boy_fixed/geom/leafpage1.json?v=2047-9d6b"}],"dispPages":[{"first":0,"count":90,"url":"https://raw.githubusercontent.com/RSCSurf/SurfMaps0/main/maps/surf_boy_fixed/geom/disppage0.json?v=2047-9d6b"}],"materialPages":[{"first":0,"count":72,"url":"https://raw.githubusercontent.com/RSCSurf/SurfMaps0/main/maps/surf_boy_fixed/materials/matpage0.json?v=2047-9d6b"}],"brushModelPages":[{"first":0,"count":1,"url":"https://raw.githubusercontent.com/RSCSurf/SurfMaps0/main/maps/surf_boy_fixed/geom/bsppage0.json?v=2047-9d6b"},{"first":1,"count":223,"url":"https://raw.githubusercontent.com/RSCSurf/SurfMaps0/main/maps/surf_boy_fixed/geom/bsppage1.json?v=2047-9d6b"}],"studioModelPages":[{"first":0,"count":1,"url":"https://raw.githubusercontent.com/RSCSurf/SurfMaps0/main/maps/surf_boy_fixed/geom/mdlpage0.json?v=2047-9d6b"}],"vertLightingPages":[{"first":0,"count":6,"url":"https://raw.githubusercontent.com/RSCSurf/SurfMaps0/main/maps/surf_boy_fixed/geom/vhvpage0.json?v=2047-9d6b"}],"visPages":[{"first":0,"count":3538,"url":"https://raw.githubusercontent.com/RSCSurf/SurfMaps0/main/maps/surf_boy_fixed/geom/vispage0.json?v=2047-9d6b"}],"ambientPages":[{"first":0,"count":4096,"url":"https://raw.githubusercontent.com/RSCSurf/SurfMaps0/main/maps/surf_boy_fixed/geom/ambientpage0.json?v=2047-9d6b"},{"first":4096,"count":4096,"url":"https://raw.githubusercontent.com/RSCSurf/SurfMaps0/main/maps/surf_boy_fixed/geom/ambientpage1.json?v=2047-9d6b"},{"first":8192,"count":1989,"url":"https://raw.githubusercontent.com/RSCSurf/SurfMaps0/main/maps/surf_boy_fixed/geom/ambientpage2.json?v=2047-9d6b"}],"entities":[{"skyMaterial":{"shader":"SourceUtils.Shaders.Sky","properties":[{"name":"cullFace","type":1,"value":false},{"name":"facePosX","type":4,"value":"https://raw.githubusercontent.com/RSCSurf/SurfMaps0/main/maps/surf_boy_fixed/materials/skybox/whitedwarfrt.vtf.json?v=2047-9d6b"},{"name":"faceNegX","type":4,"value":"https://raw.githubusercontent.com/RSCSurf/SurfMaps0/main/maps/surf_boy_fixed/materials/skybox/whitedwarflf.vtf.json?v=2047-9d6b"},{"name":"facePosY","type":4,"value":"https://raw.githubusercontent.com/RSCSurf/SurfMaps0/main/maps/surf_boy_fixed/materials/skybox/whitedwarfbk.vtf.json?v=2047-9d6b"},{"name":"faceNegY","type":4,"value":"https://raw.githubusercontent.com/RSCSurf/SurfMaps0/main/maps/surf_boy_fixed/materials/skybox/whitedwarfft.vtf.json?v=2047-9d6b"},{"name":"facePosZ","type":4,"value":"https://raw.githubusercontent.com/RSCSurf/SurfMaps0/main/maps/surf_boy_fixed/materials/skybox/whitedwarfup.vtf.json?v=2047-9d6b"},{"name":"faceNegZ","type":4,"value":"https://raw.githubusercontent.com/RSCSurf/SurfMaps0/main/maps/surf_boy_fixed/materials/skybox/whitedwarfdn.vtf.json?v=2047-9d6b"}]},"model":0,"classname":"worldspawn"},{"classname":"light","origin":{"x":-6727.0,"y":-11673.0,"z":-13850.0}},{"classname":"trigger_teleport","origin":{"x":-6089.0,"y":-11673.0,"z":-14235.5}},{"classname":"light","origin":{"x":14229.0,"y":-3817.0,"z":-5180.0}},{"classname":"light","origin":{"x":7901.0,"y":-4429.0,"z":-5180.0}},{"classname":"func_dustmotes"},{"classname":"func_dustmotes"},{"classname":"func_dustmotes"},{"model":5,"clusters":[1002,1018,1205,1223],"classname":"func_brush","origin":{"x":-6113.0,"y":9491.0,"z":4362.0}},{"model":6,"clusters":[1442,1465,2809,2816],"classname":"func_brush","origin":{"x":-6113.0,"y":173.0,"z":4362.0}},{"model":7,"clusters":[1785,1794],"classname":"func_brush","origin":{"x":15402.0,"y":-2640.0,"z":-5309.0}},{"model":8,"clusters":[2079,2088,2094,2101],"classname":"func_brush","origin":{"x":7114.0,"y":-4995.0,"z":-5309.0}},{"model":9,"clusters":[1452,1460],"classname":"func_brush","origin":{"x":-6832.0,"y":2263.0,"z":-11186.0}},{"classname":"light","origin":{"x":-10379.0,"y":7925.75,"z":-11551.9}},{"model":10,"clusters":[928,935,1343,1347,2158,2162,2722,2723,2727,2733,2738,2739,2761,2766,2774,2775,2782,2783,2784],"classname":"func_brush","origin":{"x":-916.0,"y":124.0,"z":-9129.5}},{"model":11,"clusters":[1460,1468],"classname":"func_brush","origin":{"x":-6538.0,"y":888.27,"z":-11625.7}},{"classname":"light","origin":{"x":346.0,"y":193.0,"z":-9896.0}},{"targetname":"Laser1","classname":"info_target","origin":{"x":-9344.0,"y":10279.0,"z":-11964.0},"angles":{"x":0.0,"y":270.0,"z":0.0}},{"classname":"env_laser","origin":{"x":-9344.0,"y":5069.0,"z":-11964.0}},{"classname":"env_laser","origin":{"x":-9344.0,"y":5069.0,"z":-10225.0}},{"targetname":"Laser2","classname":"info_target","origin":{"x":-9344.0,"y":10279.0,"z":-10225.0},"angles":{"x":0.0,"y":270.0,"z":0.0}},{"classname":"env_laser","origin":{"x":-11647.0,"y":5069.0,"z":-10225.0}},{"targetname":"Laser4","classname":"info_target","origin":{"x":-11647.0,"y":10277.0,"z":-11964.0},"angles":{"x":0.0,"y":270.0,"z":0.0}},{"targetname":"Laser3","classname":"info_target","origin":{"x":-11647.0,"y":10277.0,"z":-10225.0},"angles":{"x":0.0,"y":270.0,"z":0.0}},{"classname":"env_laser","origin":{"x":-11647.0,"y":5069.0,"z":-11964.0}},{"model":12,"clusters":[1611],"classname":"func_brush","origin":{"x":-9344.0,"y":5056.0,"z":-11964.0}},{"model":13,"clusters":[1623],"classname":"func_brush","origin":{"x":-11647.0,"y":5056.0,"z":-11964.0}},{"model":14,"clusters":[1623],"classname":"func_brush","origin":{"x":-11647.0,"y":5056.0,"z":-10225.0}},{"model":15,"clusters":[1611],"classname":"func_brush","origin":{"x":-9344.0,"y":5056.0,"z":-10225.0}},{"classname":"light","origin":{"x":-10504.5,"y":1126.0,"z":-10894.0}},{"classname":"trigger_teleport","origin":{"x":-12480.0,"y":-6264.5,"z":-9854.0}},{"classname":"trigger_teleport","origin":{"x":-6877.5,"y":-6258.0,"z":-9854.0}},{"classname":"trigger_teleport","origin":{"x":-14088.0,"y":974.0,"z":-10748.0}},{"classname":"trigger_teleport","origin":{"x":8600.0,"y":3228.0,"z":-1107.5}},{"targetname":"b3","classname":"info_teleport_destination","origin":{"x":8587.0,"y":15096.0,"z":1512.0},"angles":{"x":0.0,"y":270.0,"z":0.0}},{"model":20,"clusters":[72],"classname":"func_brush","origin":{"x":8052.0,"y":15097.0,"z":1368.0}},{"classname":"trigger_teleport","origin":{"x":8588.5,"y":12705.0,"z":-1592.0}},{"classname":"trigger_teleport","origin":{"x":8588.5,"y":11636.8,"z":-328.0}},{"model":23,"clusters":[18,23,40],"classname":"func_brush","origin":{"x":10214.0,"y":13625.0,"z":283.5}},{"model":24,"clusters":[76,78,84],"classname":"func_brush","origin":{"x":6963.0,"y":13625.0,"z":283.5}},{"classname":"trigger_teleport","origin":{"x":8570.5,"y":10421.5,"z":17.5}},{"classname":"trigger_teleport","origin":{"x":8588.5,"y":9894.51,"z":17.5}},{"classname":"trigger_teleport","origin":{"x":8588.0,"y":8664.1,"z":-670.0}},{"classname":"trigger_teleport","origin":{"x":7276.0,"y":8664.1,"z":-226.0}},{"classname":"trigger_teleport","origin":{"x":9900.5,"y":8664.1,"z":-226.0}},{"classname":"trigger_teleport","origin":{"x":8589.0,"y":1787.0,"z":-2844.5}},{"classname":"trigger_teleport","origin":{"x":8589.0,"y":4636.5,"z":-2083.5}},{"classname":"trigger_teleport","origin":{"x":8600.5,"y":6571.5,"z":-670.0}},{"classname":"func_areaportal"},{"classname":"func_areaportal"},{"model":33,"clusters":[706],"classname":"func_brush","origin":{"x":8600.0,"y":3228.0,"z":-539.0}},{"classname":"trigger_teleport","origin":{"x":8589.0,"y":1787.0,"z":-1263.5}},{"model":35,"clusters":[71],"classname":"func_brush","origin":{"x":9122.0,"y":15097.0,"z":1368.0}},{"classname":"trigger_teleport","origin":{"x":9315.51,"y":4409.0,"z":-831.0}},{"model":37,"clusters":[452,686],"classname":"func_brush","origin":{"x":9315.51,"y":4419.0,"z":-816.5}},{"targetname":"bonus3_end","classname":"trigger_multiple","origin":{"x":8600.5,"y":4181.0,"z":-611.5}},{"targetname":"bonus3_start","classname":"trigger_multiple","origin":{"x":8587.0,"y":15098.0,"z":1715.5}},{"model":40,"clusters":[685,696],"classname":"func_brush","origin":{"x":8589.0,"y":4584.0,"z":-973.0}},{"classname":"trigger_teleport","origin":{"x":-10099.0,"y":15092.5,"z":7341.2}},{"model":42,"clusters":[1598,1700],"classname":"func_brush","origin":{"x":-15225.0,"y":5242.0,"z":-11186.0}},{"model":43,"clusters":[1076,1493],"classname":"func_brush","origin":{"x":-11732.0,"y":9153.0,"z":4938.0}},{"model":44,"clusters":[1073,1490],"classname":"func_brush","origin":{"x":-11014.0,"y":9153.0,"z":4938.0}},{"model":45,"clusters":[2787,2795],"classname":"func_brush","origin":{"x":-2167.0,"y":-3030.04,"z":11079.6}},{"model":46,"clusters":[2178,2185],"classname":"func_brush","origin":{"x":1031.0,"y":-3030.04,"z":11079.6}},{"classname":"light","origin":{"x":-462.0,"y":205.0,"z":-9896.0}},{"classname":"light","origin":{"x":-1012.21,"y":-1297.0,"z":-9896.0}},{"classname":"light","origin":{"x":-997.194,"y":-2499.0,"z":-9896.0}},{"classname":"trigger_teleport","origin":{"x":2689.0,"y":2187.01,"z":-6516.0}},{"classname":"light","origin":{"x":-12512.4,"y":-6296.37,"z":-9346.63}},{"classname":"light","origin":{"x":-6965.25,"y":-6126.75,"z":-9352.0}},{"targetname":"b2","classname":"info_teleport_destination","origin":{"x":7111.0,"y":-11673.0,"z":-11326.0},"angles":{"x":0.0,"y":180.0,"z":0.0}},{"classname":"trigger_teleport","origin":{"x":230.5,"y":-11672.0,"z":-15083.0}},{"model":49,"clusters":[2586,2595],"classname":"func_brush","origin":{"x":1141.0,"y":-10737.0,"z":-13032.5}},{"model":50,"clusters":[2700,2706],"classname":"func_brush","origin":{"x":1141.0,"y":-12607.0,"z":-13032.5}},{"model":51,"clusters":[3379,3386,3390],"classname":"func_brush","origin":{"x":-2463.0,"y":-12607.0,"z":-13032.5}},{"model":52,"clusters":[3234,3261,3270],"classname":"func_brush","origin":{"x":-2463.0,"y":-10737.0,"z":-13032.5}},{"model":53,"clusters":[2643,2654,2667],"classname":"func_brush","origin":{"x":5462.0,"y":-12607.0,"z":-13032.5}},{"model":54,"clusters":[2439,2449,2498],"classname":"func_brush","origin":{"x":5462.01,"y":-10737.0,"z":-13032.5}},{"classname":"trigger_teleport","origin":{"x":3301.5,"y":-11672.5,"z":-13004.0}},{"classname":"trigger_teleport","origin":{"x":-302.5,"y":-11672.5,"z":-13049.0}},{"classname":"light","origin":{"x":-302.0,"y":-11672.0,"z":-12816.0}},{"classname":"light","origin":{"x":3302.0,"y":-11672.0,"z":-12748.0}},{"model":57,"clusters":[3408,3411],"classname":"func_brush","origin":{"x":-5152.0,"y":-12607.0,"z":-13032.5}},{"model":58,"clusters":[3324,3329],"classname":"func_brush","origin":{"x":-5152.0,"y":-10737.0,"z":-13032.5}},{"classname":"func_areaportal"},{"classname":"trigger_teleport","origin":{"x":7338.5,"y":-12261.0,"z":-13006.0}},{"classname":"trigger_teleport","origin":{"x":7338.5,"y":-11083.0,"z":-13006.0}},{"classname":"trigger_teleport","origin":{"x":3033.5,"y":-11073.0,"z":-13032.0}},{"classname":"trigger_teleport","origin":{"x":3033.5,"y":-12272.0,"z":-13032.0}},{"classname":"trigger_teleport","origin":{"x":-570.5,"y":-12272.0,"z":-13024.7}},{"classname":"trigger_teleport","origin":{"x":-570.5,"y":-11073.0,"z":-13024.7}},{"model":65,"clusters":[3341],"classname":"func_brush","origin":{"x":-6089.0,"y":-11673.0,"z":-13850.0}},{"model":66,"clusters":[3415,3417],"classname":"func_brush","origin":{"x":-7112.5,"y":-12550.0,"z":-14207.5}},{"classname":"trigger_teleport","origin":{"x":-7112.5,"y":-12540.0,"z":-14222.0}},{"targetname":"bonus2_end","classname":"trigger_multiple","origin":{"x":-7111.0,"y":-11672.0,"z":-14063.0}},{"targetname":"bonus2_start","classname":"trigger_multiple","origin":{"x":6907.0,"y":-11672.0,"z":-11367.0}},{"classname":"trigger_teleport","origin":{"x":-34.5,"y":-11083.0,"z":-14527.0}},{"classname":"trigger_teleport","origin":{"x":-34.5,"y":-12261.0,"z":-14527.0}},{"classname":"trigger_teleport","origin":{"x":-11146.0,"y":14671.5,"z":7341.2}},{"model":73,"clusters":[2232],"classname":"func_brush","origin":{"x":760.11,"y":-5389.89,"z":12128.5}},{"model":74,"clusters":[2731],"classname":"func_brush","origin":{"x":-568.0,"y":-2030.0,"z":9029.24}},{"classname":"func_dustmotes"},{"targetname":"stage1","classname":"trigger_teleport","origin":{"x":-14478.0,"y":9567.0,"z":-12592.0}},{"classname":"info_player_terrorist","origin":{"x":-9959.0,"y":13078.0,"z":7220.0},"angles":{"x":0.0,"y":180.0,"z":0.0}},{"classname":"info_player_terrorist","origin":{"x":-9960.0,"y":13128.0,"z":7220.0},"angles":{"x":0.0,"y":180.0,"z":0.0}},{"classname":"info_player_terrorist","origin":{"x":-9959.0,"y":13180.0,"z":7220.0},"angles":{"x":0.0,"y":180.0,"z":0.0}},{"classname":"info_player_terrorist","origin":{"x":-9960.0,"y":13240.0,"z":7220.0},"angles":{"x":0.0,"y":180.0,"z":0.0}},{"classname":"info_player_terrorist","origin":{"x":-9957.0,"y":13290.0,"z":7220.0},"angles":{"x":0.0,"y":180.0,"z":0.0}},{"classname":"info_player_terrorist","origin":{"x":-9954.0,"y":13349.0,"z":7220.0},"angles":{"x":0.0,"y":180.0,"z":0.0}},{"classname":"trigger_multiple","origin":{"x":-10090.5,"y":13719.0,"z":7312.5}},{"targetname":"hub","classname":"info_teleport_destination","origin":{"x":-10593.0,"y":13719.0,"z":7542.0},"angles":{"x":0.0,"y":180.0,"z":0.0}},{"classname":"info_player_start","origin":{"x":-10088.0,"y":13722.0,"z":7344.0},"angles":{"x":0.0,"y":180.0,"z":0.0}},{"classname":"info_player_counterterrorist","origin":{"x":-10145.0,"y":14034.5,"z":7220.0},"angles":{"x":0.0,"y":180.0,"z":0.0}},{"classname":"info_player_counterterrorist","origin":{"x":-10144.0,"y":14090.5,"z":7220.0},"angles":{"x":0.0,"y":180.0,"z":0.0}},{"classname":"info_player_counterterrorist","origin":{"x":-10053.0,"y":14425.5,"z":7220.0},"angles":{"x":0.0,"y":180.0,"z":0.0}},{"classname":"info_player_counterterrorist","origin":{"x":-9979.0,"y":14426.5,"z":7220.0},"angles":{"x":0.0,"y":180.0,"z":0.0}},{"classname":"info_player_counterterrorist","origin":{"x":-9981.0,"y":14367.5,"z":7220.0},"angles":{"x":0.0,"y":180.0,"z":0.0}},{"classname":"info_player_counterterrorist","origin":{"x":-10055.0,"y":14366.5,"z":7220.0},"angles":{"x":0.0,"y":180.0,"z":0.0}},{"classname":"info_player_counterterrorist","origin":{"x":-10056.0,"y":14316.5,"z":7220.0},"angles":{"x":0.0,"y":180.0,"z":0.0}},{"classname":"info_player_counterterrorist","origin":{"x":-9982.0,"y":14317.5,"z":7220.0},"angles":{"x":0.0,"y":180.0,"z":0.0}},{"classname":"info_player_counterterrorist","origin":{"x":-9983.0,"y":14261.5,"z":7220.0},"angles":{"x":0.0,"y":180.0,"z":0.0}},{"classname":"info_player_counterterrorist","origin":{"x":-10057.0,"y":14260.5,"z":7220.0},"angles":{"x":0.0,"y":180.0,"z":0.0}},{"classname":"info_player_counterterrorist","origin":{"x":-10059.0,"y":14200.5,"z":7220.0},"angles":{"x":0.0,"y":180.0,"z":0.0}},{"classname":"info_player_counterterrorist","origin":{"x":-9985.0,"y":14201.5,"z":7220.0},"angles":{"x":0.0,"y":180.0,"z":0.0}},{"classname":"info_player_counterterrorist","origin":{"x":-10061.0,"y":14141.5,"z":7220.0},"angles":{"x":0.0,"y":180.0,"z":0.0}},{"classname":"info_player_counterterrorist","origin":{"x":-9987.0,"y":14142.5,"z":7220.0},"angles":{"x":0.0,"y":180.0,"z":0.0}},{"classname":"info_player_counterterrorist","origin":{"x":-9988.0,"y":14092.5,"z":7220.0},"angles":{"x":0.0,"y":180.0,"z":0.0}},{"classname":"info_player_counterterrorist","origin":{"x":-10062.0,"y":14091.5,"z":7220.0},"angles":{"x":0.0,"y":180.0,"z":0.0}},{"classname":"info_player_counterterrorist","origin":{"x":-10063.0,"y":14035.5,"z":7220.0},"angles":{"x":0.0,"y":180.0,"z":0.0}},{"classname":"info_player_counterterrorist","origin":{"x":-9989.0,"y":14036.5,"z":7220.0},"angles":{"x":0.0,"y":180.0,"z":0.0}},{"classname":"info_player_counterterrorist","origin":{"x":-10219.0,"y":14033.5,"z":7220.0},"angles":{"x":0.0,"y":180.0,"z":0.0}},{"classname":"info_player_counterterrorist","origin":{"x":-10218.0,"y":14089.5,"z":7220.0},"angles":{"x":0.0,"y":180.0,"z":0.0}},{"classname":"info_player_counterterrorist","origin":{"x":-10217.0,"y":14139.5,"z":7220.0},"angles":{"x":0.0,"y":180.0,"z":0.0}},{"classname":"info_player_counterterrorist","origin":{"x":-10215.0,"y":14198.5,"z":7220.0},"angles":{"x":0.0,"y":180.0,"z":0.0}},{"classname":"info_player_counterterrorist","origin":{"x":-10219.0,"y":14252.5,"z":7220.0},"angles":{"x":0.0,"y":180.0,"z":0.0}},{"classname":"info_player_counterterrorist","origin":{"x":-10218.0,"y":14308.5,"z":7220.0},"angles":{"x":0.0,"y":180.0,"z":0.0}},{"classname":"info_player_counterterrorist","origin":{"x":-10217.0,"y":14358.5,"z":7220.0},"angles":{"x":0.0,"y":180.0,"z":0.0}},{"classname":"info_player_counterterrorist","origin":{"x":-10215.0,"y":14417.5,"z":7220.0},"angles":{"x":0.0,"y":180.0,"z":0.0}},{"classname":"info_player_counterterrorist","origin":{"x":-10141.0,"y":14418.5,"z":7220.0},"angles":{"x":0.0,"y":180.0,"z":0.0}},{"classname":"info_player_counterterrorist","origin":{"x":-10143.0,"y":14359.5,"z":7220.0},"angles":{"x":0.0,"y":180.0,"z":0.0}},{"classname":"info_player_counterterrorist","origin":{"x":-10144.0,"y":14309.5,"z":7220.0},"angles":{"x":0.0,"y":180.0,"z":0.0}},{"classname":"info_player_counterterrorist","origin":{"x":-10145.0,"y":14253.5,"z":7220.0},"angles":{"x":0.0,"y":180.0,"z":0.0}},{"classname":"info_player_counterterrorist","origin":{"x":-10141.0,"y":14199.5,"z":7220.0},"angles":{"x":0.0,"y":180.0,"z":0.0}},{"classname":"info_player_counterterrorist","origin":{"x":-10143.0,"y":14140.5,"z":7220.0},"angles":{"x":0.0,"y":180.0,"z":0.0}},{"Brightness":{"R":245,"G":241,"B":214,"A":200},"Ambient":{"R":175,"G":205,"B":228,"A":100},"BrightnessHdr":{"R":255,"G":255,"B":255,"A":1},"AmbientHdr":{"R":255,"G":255,"B":255,"A":1},"BrightnessScaleHdr":1.0,"AmbientScaleHdr":1.5,"Pitch":-62.0,"classname":"light_environment","origin":{"x":-9947.72,"y":13141.0,"z":7641.0},"angles":{"x":-62.0,"y":197.0,"z":0.0}},{"classname":"func_dustmotes"},{"classname":"trigger_teleport","origin":{"x":-11146.0,"y":12705.5,"z":7341.2}},{"classname":"trigger_teleport","origin":{"x":-11069.5,"y":13719.5,"z":5847.97}},{"classname":"env_cascade_light","origin":{"x":-9950.19,"y":13307.0,"z":7642.0},"angles":{"x":0.0,"y":0.0,"z":0.0}},{"classname":"info_player_terrorist","origin":{"x":-10210.0,"y":13297.0,"z":7220.0},"angles":{"x":0.0,"y":180.0,"z":0.0}},{"classname":"info_player_terrorist","origin":{"x":-10207.0,"y":13356.0,"z":7220.0},"angles":{"x":0.0,"y":180.0,"z":0.0}},{"classname":"info_player_terrorist","origin":{"x":-10213.0,"y":13247.0,"z":7220.0},"angles":{"x":0.0,"y":180.0,"z":0.0}},{"classname":"info_player_terrorist","origin":{"x":-10212.0,"y":13187.0,"z":7220.0},"angles":{"x":0.0,"y":180.0,"z":0.0}},{"classname":"info_player_terrorist","origin":{"x":-10213.0,"y":13135.0,"z":7220.0},"angles":{"x":0.0,"y":180.0,"z":0.0}},{"classname":"info_player_terrorist","origin":{"x":-10212.0,"y":13085.0,"z":7220.0},"angles":{"x":0.0,"y":180.0,"z":0.0}},{"classname":"info_player_terrorist","origin":{"x":-10218.0,"y":13023.0,"z":7220.0},"angles":{"x":0.0,"y":180.0,"z":0.0}},{"classname":"info_player_terrorist","origin":{"x":-10132.0,"y":13290.0,"z":7220.0},"angles":{"x":0.0,"y":180.0,"z":0.0}},{"classname":"info_player_terrorist","origin":{"x":-10129.0,"y":13349.0,"z":7220.0},"angles":{"x":0.0,"y":180.0,"z":0.0}},{"classname":"info_player_terrorist","origin":{"x":-10135.0,"y":13240.0,"z":7220.0},"angles":{"x":0.0,"y":180.0,"z":0.0}},{"classname":"info_player_terrorist","origin":{"x":-10134.0,"y":13180.0,"z":7220.0},"angles":{"x":0.0,"y":180.0,"z":0.0}},{"classname":"info_player_terrorist","origin":{"x":-10135.0,"y":13128.0,"z":7220.0},"angles":{"x":0.0,"y":180.0,"z":0.0}},{"classname":"info_player_terrorist","origin":{"x":-10134.0,"y":13078.0,"z":7220.0},"angles":{"x":0.0,"y":180.0,"z":0.0}},{"classname":"info_player_terrorist","origin":{"x":-10140.0,"y":13016.0,"z":7220.0},"angles":{"x":0.0,"y":180.0,"z":0.0}},{"classname":"info_player_terrorist","origin":{"x":-10039.0,"y":13292.0,"z":7220.0},"angles":{"x":0.0,"y":180.0,"z":0.0}},{"classname":"info_player_terrorist","origin":{"x":-10036.0,"y":13351.0,"z":7220.0},"angles":{"x":0.0,"y":180.0,"z":0.0}},{"classname":"info_player_terrorist","origin":{"x":-10042.0,"y":13242.0,"z":7220.0},"angles":{"x":0.0,"y":180.0,"z":0.0}},{"classname":"info_player_terrorist","origin":{"x":-10041.0,"y":13182.0,"z":7220.0},"angles":{"x":0.0,"y":180.0,"z":0.0}},{"classname":"info_player_terrorist","origin":{"x":-10042.0,"y":13130.0,"z":7220.0},"angles":{"x":0.0,"y":180.0,"z":0.0}},{"classname":"info_player_terrorist","origin":{"x":-10041.0,"y":13080.0,"z":7220.0},"angles":{"x":0.0,"y":180.0,"z":0.0}},{"classname":"info_player_terrorist","origin":{"x":-10047.0,"y":13018.0,"z":7220.0},"angles":{"x":0.0,"y":180.0,"z":0.0}},{"classname":"info_player_terrorist","origin":{"x":-9965.0,"y":13016.0,"z":7220.0},"angles":{"x":0.0,"y":180.0,"z":0.0}},{"targetname":"no_falldmg","classname":"filter_damage_type","origin":{"x":-10001.5,"y":13166.0,"z":7604.0}},{"targetname":"servercommands","classname":"point_servercommand","origin":{"x":-10001.5,"y":13182.0,"z":7604.0}},{"classname":"logic_auto","origin":{"x":-10001.5,"y":13198.0,"z":7604.0}},{"targetname":"@tonemap","classname":"env_tonemap_controller","origin":{"x":-10001.5,"y":13214.0,"z":7604.0}},{"model":81,"clusters":[1037],"classname":"func_brush","origin":{"x":-10564.0,"y":13720.0,"z":7416.0}},{"classname":"info_player_counterterrorist","origin":{"x":-9914.0,"y":14429.0,"z":7220.0},"angles":{"x":0.0,"y":180.0,"z":0.0}},{"classname":"info_player_counterterrorist","origin":{"x":-9916.0,"y":14370.0,"z":7220.0},"angles":{"x":0.0,"y":180.0,"z":0.0}},{"classname":"info_player_counterterrorist","origin":{"x":-9917.0,"y":14320.0,"z":7220.0},"angles":{"x":0.0,"y":180.0,"z":0.0}},{"classname":"info_player_counterterrorist","origin":{"x":-9918.0,"y":14264.0,"z":7220.0},"angles":{"x":0.0,"y":180.0,"z":0.0}},{"classname":"info_player_counterterrorist","origin":{"x":-9920.0,"y":14204.0,"z":7220.0},"angles":{"x":0.0,"y":180.0,"z":0.0}},{"classname":"info_player_counterterrorist","origin":{"x":-9922.0,"y":14145.0,"z":7220.0},"angles":{"x":0.0,"y":180.0,"z":0.0}},{"classname":"info_player_counterterrorist","origin":{"x":-9923.0,"y":14095.0,"z":7220.0},"angles":{"x":0.0,"y":180.0,"z":0.0}},{"classname":"info_player_counterterrorist","origin":{"x":-9924.0,"y":14039.0,"z":7220.0},"angles":{"x":0.0,"y":180.0,"z":0.0}},{"classname":"info_player_terrorist","origin":{"x":-9880.0,"y":13351.0,"z":7220.0},"angles":{"x":0.0,"y":180.0,"z":0.0}},{"classname":"info_player_terrorist","origin":{"x":-9883.0,"y":13292.0,"z":7220.0},"angles":{"x":0.0,"y":180.0,"z":0.0}},{"classname":"info_player_terrorist","origin":{"x":-9886.0,"y":13242.0,"z":7220.0},"angles":{"x":0.0,"y":180.0,"z":0.0}},{"classname":"info_player_terrorist","origin":{"x":-9885.0,"y":13182.0,"z":7220.0},"angles":{"x":0.0,"y":180.0,"z":0.0}},{"classname":"info_player_terrorist","origin":{"x":-9886.0,"y":13130.0,"z":7220.0},"angles":{"x":0.0,"y":180.0,"z":0.0}},{"classname":"info_player_terrorist","origin":{"x":-9885.0,"y":13080.0,"z":7220.0},"angles":{"x":0.0,"y":180.0,"z":0.0}},{"classname":"info_player_terrorist","origin":{"x":-9891.0,"y":13018.0,"z":7220.0},"angles":{"x":0.0,"y":180.0,"z":0.0}},{"model":82,"clusters":[3070],"classname":"func_brush","origin":{"x":-10217.5,"y":-6959.0,"z":14439.0}},{"model":83,"clusters":[3078,3081,3094,3097],"classname":"func_brush","origin":{"x":-10638.0,"y":-7036.0,"z":14459.0}},{"classname":"trigger_multiple","origin":{"x":-7627.0,"y":-6536.0,"z":12520.0}},{"classname":"trigger_multiple","origin":{"x":-10355.0,"y":-7452.5,"z":12804.0}},{"targetname":"filter_cp1_boy","classname":"filter_activator_name","origin":{"x":-7240.0,"y":-6669.0,"z":11393.5}},{"classname":"trigger_multiple","origin":{"x":-11025.0,"y":-6743.5,"z":13781.0}},{"classname":"trigger_multiple","origin":{"x":-9490.0,"y":-4810.0,"z":14235.5}},{"targetname":"filter_cp2_boy","classname":"filter_activator_name","origin":{"x":-7245.0,"y":-6745.0,"z":11393.5}},{"targetname":"filter_cp3_boy","classname":"filter_activator_name","origin":{"x":-7243.0,"y":-6824.0,"z":11393.5}},{"classname":"trigger_teleport","origin":{"x":-9282.0,"y":-6391.0,"z":11966.5}},{"model":89,"clusters":[3078],"classname":"func_brush","origin":{"x":-10466.0,"y":-6668.5,"z":14432.0}},{"classname":"trigger_teleport","origin":{"x":-10466.0,"y":-6692.0,"z":14432.0}},{"targetname":"bonus1_end","classname":"trigger_multiple","origin":{"x":-10466.5,"y":-7035.5,"z":14633.5}},{"model":92,"clusters":[2948,2950],"classname":"func_brush","origin":{"x":-7148.0,"y":-6529.0,"z":12331.3}},{"targetname":"b1_cp2","classname":"info_teleport_destination","origin":{"x":-10826.0,"y":-6461.0,"z":13867.0},"angles":{"x":0.0,"y":270.0,"z":0.0}},{"targetname":"b1_cp1","classname":"info_teleport_destination","origin":{"x":-10834.0,"y":-7460.0,"z":12921.0},"angles":{"x":0.0,"y":0.0,"z":0.0}},{"classname":"trigger_teleport","origin":{"x":-9282.0,"y":-6391.0,"z":12000.5}},{"classname":"trigger_teleport","origin":{"x":-9282.0,"y":-6391.0,"z":12017.5}},{"targetname":"bonus1_start","classname":"trigger_multiple","origin":{"x":-7623.0,"y":-6532.0,"z":12524.0}},{"targetname":"b1_cp3","classname":"info_teleport_destination","origin":{"x":-9078.0,"y":-4869.0,"z":14265.0},"angles":{"x":0.0,"y":180.0,"z":0.0}},{"classname":"func_dustmotes"},{"classname":"trigger_teleport","origin":{"x":-9282.0,"y":-6391.0,"z":11983.5}},{"targetname":"b1","classname":"info_teleport_destination","origin":{"x":-7627.63,"y":-6528.0,"z":12576.0},"angles":{"x":0.0,"y":90.0,"z":0.0}},{"classname":"func_dustmotes"},{"model":99,"clusters":[1076],"classname":"func_brush","origin":{"x":-11376.0,"y":9514.0,"z":5038.0}},{"classname":"trigger_teleport","origin":{"x":-11787.5,"y":13700.0,"z":7341.2}},{"classname":"trigger_teleport","origin":{"x":-1262.0,"y":-8376.0,"z":-11281.0}},{"classname":"trigger_teleport","origin":{"x":-4769.0,"y":-8376.0,"z":-11281.0}},{"classname":"func_dustmotes"},{"classname":"func_dustmotes"},{"targetname":"stage2_cont","classname":"info_teleport_destination","origin":{"x":-564.0,"y":-8978.0,"z":15739.0},"angles":{"x":0.0,"y":270.0,"z":0.0}},{"model":105,"clusters":[3248,3272,3277,3374,3383,3387],"classname":"func_brush","origin":{"x":-2412.0,"y":-12328.0,"z":13327.1}},{"model":106,"clusters":[2565,2597,2601,2607,2680,2687,2696,2702],"classname":"func_brush","origin":{"x":1260.0,"y":-12328.0,"z":13327.1}},{"model":107,"clusters":[2608,2703,3237,3249,3365,3373,3375],"classname":"func_brush","origin":{"x":-576.0,"y":-12328.0,"z":10388.0}},{"model":108,"clusters":[2471,2483,2506,2517,2525,2530,2534,2536,2540,2543,2545,2549,2552,2556,2560,2565,2572,2576,2579,2588,2597,2601,2607,2670,2679,2680,2686,2687,2696,2702,2709,2710,2711,2712,2713,2714,2715,2716,2717,2718,3178,3181,3185,3189,3193,3198,3203,3207,3211,3216,3227,3236,3248,3254,3263,3272,3277,3282,3291,3317,3334,3365,3372,3374,3381,3382,3383,3387,3393,3394,3395,3396,3397,3398,3399,3400,3401,3402,3403,3412,3418,3419],"classname":"func_brush","origin":{"x":-569.5,"y":-12327.5,"z":16217.0}},{"classname":"trigger_teleport","origin":{"x":-569.5,"y":-12327.5,"z":13327.0}},{"classname":"trigger_teleport","origin":{"x":-569.5,"y":-14487.5,"z":10410.5}},{"classname":"trigger_teleport","origin":{"x":-569.5,"y":-10168.0,"z":10410.5}},{"classname":"trigger_teleport","origin":{"x":-2906.5,"y":-12328.0,"z":10410.5}},{"classname":"trigger_teleport","origin":{"x":1761.0,"y":-12328.0,"z":10410.5}},{"classname":"trigger_teleport","origin":{"x":-569.5,"y":-7635.5,"z":5921.0}},{"model":115,"clusters":[3248,3374],"classname":"func_brush","origin":{"x":-1499.0,"y":-12361.0,"z":10513.0}},{"model":116,"clusters":[2607,2608,2702,2703],"classname":"func_brush","origin":{"x":347.0,"y":-12361.0,"z":10513.0}},{"model":117,"clusters":[2165,2168,2177,2180,2184,2190,2730,2735,2750,2758,2763,2769,2777,2786,2794],"classname":"func_brush","origin":{"x":-568.0,"y":-3030.5,"z":11772.0}},{"classname":"func_areaportal"},{"classname":"trigger_teleport","origin":{"x":-1148.0,"y":-5653.5,"z":11998.0}},{"targetname":"stage2_end","classname":"trigger_multiple","origin":{"x":-568.0,"y":-4150.0,"z":12985.0}},{"classname":"trigger_teleport","origin":{"x":-6909.5,"y":9371.49,"z":-11759.5}},{"classname":"trigger_teleport","origin":{"x":-6159.5,"y":9371.49,"z":-11759.5}},{"classname":"trigger_teleport","origin":{"x":-4769.0,"y":3912.0,"z":-11281.0}},{"classname":"trigger_teleport","origin":{"x":56.0,"y":2014.0,"z":3491.0}},{"classname":"light","origin":{"x":4353.0,"y":2187.0,"z":-6307.75}},{"classname":"light","origin":{"x":845.0,"y":3833.0,"z":-6307.75}},{"classname":"light","origin":{"x":909.0,"y":20.0,"z":-6308.0}},{"model":124,"clusters":[3196,3197,3201,3202],"classname":"func_brush","origin":{"x":-3015.0,"y":-9109.5,"z":-8800.0}},{"classname":"trigger_teleport","origin":{"x":-3015.0,"y":-9152.0,"z":-8800.0}},{"classname":"light","origin":{"x":-2864.0,"y":-7898.0,"z":-9745.05}},{"classname":"light","origin":{"x":-3013.0,"y":-4701.0,"z":-9745.05}},{"classname":"light","origin":{"x":1025.0,"y":8452.25,"z":-6533.0}},{"classname":"light","origin":{"x":-3058.29,"y":8446.6,"z":-5667.5}},{"classname":"light","origin":{"x":-12946.0,"y":8451.25,"z":-3263.0}},{"classname":"light","origin":{"x":-12946.0,"y":2225.25,"z":-3263.0}},{"classname":"trigger_teleport","origin":{"x":-1036.5,"y":5335.0,"z":-7551.0}},{"classname":"trigger_teleport","origin":{"x":-12940.0,"y":5335.0,"z":-5057.0}},{"classname":"trigger_teleport","origin":{"x":-7573.5,"y":5335.0,"z":-5046.0}},{"classname":"light","origin":{"x":1025.0,"y":9717.0,"z":-6533.0}},{"classname":"light","origin":{"x":1025.0,"y":7586.0,"z":-6533.0}},{"classname":"light","origin":{"x":-1777.0,"y":8449.75,"z":-6108.25}},{"model":129,"clusters":[918,920,2152,2153],"classname":"func_brush","origin":{"x":2688.5,"y":20.0,"z":-5602.0}},{"model":130,"clusters":[662,664,856,858,864,866],"classname":"func_brush","origin":{"x":2688.5,"y":4354.0,"z":-5602.0}},{"model":131,"clusters":[769,770,816,817,829,830,836,837,851,852,854,855,885,886,888,889,891,892,894,895,897,898,900,901],"classname":"func_brush","origin":{"x":4353.0,"y":2187.0,"z":-7705.5}},{"classname":"light","origin":{"x":-2854.33,"y":2219.0,"z":-5965.0}},{"classname":"light","origin":{"x":4177.0,"y":20.0,"z":-6307.75}},{"classname":"light","origin":{"x":4177.0,"y":4354.0,"z":-6307.75}},{"classname":"trigger_teleport","origin":{"x":4177.0,"y":2187.0,"z":-7644.0}},{"classname":"func_areaportal"},{"classname":"light","origin":{"x":3465.0,"y":2207.15,"z":-9895.66}},{"classname":"light","origin":{"x":3468.0,"y":933.0,"z":-9895.66}},{"classname":"light","origin":{"x":3463.0,"y":3437.0,"z":-9895.66}},{"classname":"light","origin":{"x":-3232.0,"y":3437.0,"z":-9896.0}},{"classname":"light","origin":{"x":-3230.0,"y":2207.15,"z":-9896.0}},{"classname":"light","origin":{"x":-3227.0,"y":933.0,"z":-9896.0}},{"classname":"light","origin":{"x":-2154.88,"y":-2534.5,"z":-9896.0}},{"classname":"light","origin":{"x":-2827.35,"y":-2536.5,"z":-9896.0}},{"classname":"light","origin":{"x":-4101.5,"y":-2539.5,"z":-9896.0}},{"classname":"trigger_teleport","origin":{"x":40.5,"y":2206.5,"z":-11485.0}},{"classname":"trigger_teleport","origin":{"x":-3015.5,"y":-4673.5,"z":-11485.0}},{"classname":"trigger_teleport","origin":{"x":-13546.0,"y":10832.0,"z":-4845.0}},{"classname":"trigger_teleport","origin":{"x":-13546.0,"y":-162.0,"z":-4845.0}},{"classname":"light","origin":{"x":1028.0,"y":8469.25,"z":-2265.18}},{"classname":"light","origin":{"x":1028.0,"y":8352.0,"z":-293.0}},{"classname":"trigger_teleport","origin":{"x":-504.5,"y":2080.0,"z":3286.5}},{"classname":"trigger_teleport","origin":{"x":-2480.0,"y":8352.0,"z":3286.5}},{"classname":"trigger_teleport","origin":{"x":-879.0,"y":8352.0,"z":3286.5}},{"classname":"trigger_teleport","origin":{"x":2081.0,"y":8352.0,"z":3286.5}},{"classname":"trigger_teleport","origin":{"x":601.0,"y":7147.0,"z":3286.5}},{"classname":"trigger_teleport","origin":{"x":601.0,"y":9557.0,"z":3286.5}},{"classname":"trigger_teleport","origin":{"x":174.5,"y":8352.0,"z":3286.5}},{"classname":"trigger_teleport","origin":{"x":1027.5,"y":8352.0,"z":974.5}},{"classname":"trigger_teleport","origin":{"x":174.5,"y":8352.0,"z":-1337.5}},{"classname":"trigger_teleport","origin":{"x":1027.5,"y":8352.0,"z":-3650.5}},{"classname":"func_areaportal"},{"classname":"trigger_teleport","origin":{"x":-262.0,"y":8431.0,"z":-5198.0}},{"classname":"trigger_teleport","origin":{"x":10267.0,"y":183.5,"z":2566.5}},{"classname":"trigger_teleport","origin":{"x":5423.0,"y":-4679.5,"z":3684.0}},{"classname":"func_areaportal"},{"classname":"light","origin":{"x":-9740.0,"y":7672.0,"z":-10894.0}},{"classname":"light","origin":{"x":-13954.0,"y":7672.0,"z":-10894.0}},{"classname":"light","origin":{"x":-2849.0,"y":8025.0,"z":-10894.0}},{"classname":"func_dustmotes"},{"targetname":"stage1_start","classname":"trigger_multiple","origin":{"x":-11373.0,"y":9153.0,"z":5089.0}},{"targetname":"stage1_end","classname":"trigger_multiple","origin":{"x":-9682.0,"y":-6258.0,"z":-9154.0}},{"targetname":"stage2","classname":"info_teleport_destination","origin":{"x":12518.0,"y":13987.0,"z":13692.0},"angles":{"x":0.0,"y":270.0,"z":0.0}},{"classname":"func_dustmotes"},{"targetname":"stage2_start","classname":"trigger_multiple","origin":{"x":12518.0,"y":14227.0,"z":13648.0}},{"classname":"trigger_teleport","origin":{"x":12521.5,"y":11828.0,"z":10864.0}},{"classname":"trigger_teleport","origin":{"x":10564.5,"y":6354.5,"z":10864.0}},{"classname":"trigger_teleport","origin":{"x":14476.5,"y":6354.5,"z":10864.0}},{"classname":"trigger_teleport","origin":{"x":12521.5,"y":4382.5,"z":10864.0}},{"classname":"trigger_teleport","origin":{"x":12519.5,"y":6354.5,"z":13821.5}},{"classname":"trigger_teleport","origin":{"x":13774.5,"y":6354.5,"z":12017.0}},{"classname":"trigger_teleport","origin":{"x":11264.5,"y":6354.5,"z":12017.0}},{"classname":"func_areaportal"},{"classname":"func_areaportal"},{"classname":"func_areaportal"},{"classname":"trigger_teleport","origin":{"x":12520.0,"y":6355.0,"z":9934.0}},{"classname":"light","origin":{"x":8325.34,"y":571.25,"z":-5433.34}},{"classname":"trigger_teleport","origin":{"x":1037.0,"y":7672.0,"z":-13585.5}},{"classname":"trigger_teleport","origin":{"x":7785.0,"y":8603.5,"z":-13585.5}},{"classname":"trigger_teleport","origin":{"x":5888.5,"y":5972.49,"z":-12562.5}},{"classname":"trigger_teleport","origin":{"x":-816.5,"y":9371.49,"z":-12562.5}},{"model":167,"clusters":[554,559],"classname":"func_brush","origin":{"x":8309.0,"y":6587.0,"z":-10098.0}},{"classname":"light","origin":{"x":8810.0,"y":-13046.0,"z":-7655.0}},{"classname":"light","origin":{"x":8808.0,"y":-8585.0,"z":-7655.0}},{"classname":"trigger_teleport","origin":{"x":8809.0,"y":-13047.5,"z":-8179.5}},{"classname":"trigger_teleport","origin":{"x":8809.0,"y":-8584.5,"z":-8179.5}},{"classname":"trigger_teleport","origin":{"x":-10881.5,"y":7672.0,"z":-12782.5}},{"classname":"trigger_teleport","origin":{"x":-14088.0,"y":2193.5,"z":-12782.5}},{"classname":"trigger_teleport","origin":{"x":-9739.5,"y":1338.0,"z":-12782.5}},{"classname":"trigger_teleport","origin":{"x":-5034.5,"y":7672.0,"z":-13184.0}},{"classname":"light","origin":{"x":-10201.0,"y":-5504.0,"z":-9012.0}},{"classname":"light","origin":{"x":-10201.0,"y":-3513.0,"z":-9477.0}},{"classname":"light","origin":{"x":-10201.0,"y":-1882.0,"z":-10137.0}},{"model":174,"clusters":[3072],"classname":"func_brush","origin":{"x":-9681.5,"y":-6556.0,"z":-9328.68}},{"classname":"trigger_teleport","origin":{"x":-9682.0,"y":-3740.0,"z":-11736.5}},{"classname":"trigger_teleport","origin":{"x":-9682.0,"y":-707.0,"z":-11757.5}},{"classname":"trigger_teleport","origin":{"x":-9681.5,"y":-6556.0,"z":-9328.61}},{"classname":"light","origin":{"x":-8252.0,"y":1073.0,"z":-10894.0}},{"classname":"func_areaportal"},{"classname":"trigger_teleport","origin":{"x":8308.0,"y":6624.0,"z":-11401.0}},{"classname":"trigger_teleport","origin":{"x":14229.0,"y":-8379.0,"z":-5805.5}},{"classname":"func_areaportal"},{"classname":"trigger_teleport","origin":{"x":11258.0,"y":-3154.0,"z":-6303.0}},{"classname":"light","origin":{"x":-446.0,"y":-9997.0,"z":-4353.0}},{"classname":"light","origin":{"x":-446.0,"y":-11535.0,"z":-4353.0}},{"classname":"light","origin":{"x":7533.0,"y":2747.0,"z":-7270.0}},{"classname":"light","origin":{"x":8308.0,"y":3522.0,"z":-7270.0}},{"classname":"trigger_teleport","origin":{"x":9464.0,"y":2746.0,"z":-6303.0}},{"classname":"trigger_teleport","origin":{"x":7155.0,"y":2744.0,"z":-6303.0}},{"classname":"trigger_teleport","origin":{"x":7533.0,"y":2746.5,"z":-6046.0}},{"classname":"trigger_teleport","origin":{"x":9084.0,"y":2747.0,"z":-6046.0}},{"classname":"trigger_teleport","origin":{"x":8308.0,"y":1971.0,"z":-6046.0}},{"classname":"trigger_teleport","origin":{"x":8308.0,"y":3523.0,"z":-6046.0}},{"classname":"trigger_teleport","origin":{"x":6757.0,"y":5074.0,"z":-7933.0}},{"classname":"trigger_teleport","origin":{"x":7533.0,"y":4298.0,"z":-7933.0}},{"classname":"trigger_teleport","origin":{"x":5982.0,"y":4297.5,"z":-7933.0}},{"classname":"trigger_teleport","origin":{"x":6757.0,"y":3522.0,"z":-7933.0}},{"classname":"trigger_teleport","origin":{"x":8308.0,"y":6625.0,"z":-9820.0}},{"classname":"trigger_teleport","origin":{"x":9084.0,"y":5849.0,"z":-9820.0}},{"classname":"trigger_teleport","origin":{"x":7533.0,"y":5848.5,"z":-9820.0}},{"classname":"trigger_teleport","origin":{"x":8308.0,"y":5073.0,"z":-9820.0}},{"classname":"light","origin":{"x":6953.0,"y":4599.0,"z":-9283.0}},{"classname":"light","origin":{"x":8308.0,"y":5081.0,"z":-9283.0}},{"classname":"trigger_teleport","origin":{"x":7878.72,"y":2714.02,"z":-8334.0}},{"classname":"trigger_teleport","origin":{"x":8687.38,"y":4297.0,"z":-8334.0}},{"classname":"trigger_teleport","origin":{"x":7878.72,"y":4265.02,"z":-10292.0}},{"classname":"trigger_teleport","origin":{"x":6724.38,"y":5848.0,"z":-10292.0}},{"classname":"trigger_teleport","origin":{"x":9464.0,"y":5848.0,"z":-10292.0}},{"classname":"light","origin":{"x":2752.0,"y":-9997.0,"z":-4465.0}},{"classname":"light","origin":{"x":5735.0,"y":-10021.0,"z":-4734.0}},{"classname":"light","origin":{"x":5735.0,"y":-11611.0,"z":-4734.0}},{"classname":"trigger_teleport","origin":{"x":5735.0,"y":-10816.0,"z":-5728.0}},{"classname":"trigger_teleport","origin":{"x":2621.5,"y":-10816.0,"z":-5728.0}},{"model":202,"clusters":[2127,2135,2139,2209,2365,2385,2389,2468],"classname":"func_brush","origin":{"x":5735.0,"y":-8380.0,"z":-6308.5}},{"model":203,"clusters":[2623,2632,2638,2651,2655,2657,2664,2677],"classname":"func_brush","origin":{"x":5735.0,"y":-13252.0,"z":-6308.5}},{"classname":"func_areaportal"},{"classname":"trigger_teleport","origin":{"x":5867.0,"y":-10816.0,"z":-9232.0}},{"classname":"trigger_teleport","origin":{"x":10002.0,"y":-10816.0,"z":-9213.5}},{"classname":"trigger_teleport","origin":{"x":14229.5,"y":-10814.5,"z":-9213.5}},{"classname":"func_dustmotes"},{"classname":"light","origin":{"x":5867.0,"y":-10816.0,"z":-7655.0}},{"classname":"light","origin":{"x":4926.0,"y":-11624.0,"z":-7655.0}},{"classname":"light","origin":{"x":4927.0,"y":-10007.0,"z":-7655.0}},{"classname":"light","origin":{"x":5735.0,"y":-12433.0,"z":-7655.0}},{"classname":"light","origin":{"x":5735.0,"y":-9199.0,"z":-7655.0}},{"classname":"trigger_teleport","origin":{"x":1516.0,"y":-10816.0,"z":-4693.5}},{"classname":"trigger_teleport","origin":{"x":3986.0,"y":-10816.0,"z":-5230.5}},{"classname":"trigger_teleport","origin":{"x":5735.0,"y":-9067.0,"z":-5230.5}},{"classname":"trigger_teleport","origin":{"x":5735.0,"y":-12565.0,"z":-5230.5}},{"classname":"light","origin":{"x":2752.0,"y":-11587.0,"z":-4465.0}},{"targetname":"stage1","classname":"info_teleport_destination","origin":{"x":-11373.1,"y":8913.0,"z":5202.0},"angles":{"x":0.0,"y":270.0,"z":0.0}},{"classname":"func_dustmotes"},{"classname":"trigger_teleport","origin":{"x":-11373.0,"y":957.0,"z":1296.0}},{"classname":"trigger_teleport","origin":{"x":-11373.0,"y":-9256.0,"z":1296.0}},{"classname":"trigger_teleport","origin":{"x":-13848.5,"y":-11108.0,"z":1296.0}},{"classname":"trigger_teleport","origin":{"x":-8929.5,"y":-11108.0,"z":1296.0}},{"classname":"trigger_teleport","origin":{"x":-11405.0,"y":-11908.0,"z":1296.0}},{"classname":"trigger_teleport","origin":{"x":-11405.0,"y":-10760.0,"z":1398.0}},{"classname":"trigger_teleport","origin":{"x":-9570.0,"y":-10816.0,"z":-3928.0}},{"classname":"trigger_teleport","origin":{"x":-11320.0,"y":-10816.0,"z":-1536.0}},{"classname":"trigger_teleport","origin":{"x":-5720.0,"y":-9961.0,"z":-8474.5}},{"classname":"trigger_teleport","origin":{"x":-5720.0,"y":-11671.0,"z":-8474.5}},{"classname":"func_areaportal"},{"classname":"trigger_teleport","origin":{"x":-5720.0,"y":-10816.0,"z":-8536.0}},{"index":0,"clusters":[1033],"classname":"displacement"},{"index":1,"clusters":[1033,1035],"classname":"displacement"},{"index":2,"clusters":[1033,1035],"classname":"displacement"},{"index":3,"clusters":[1033,1035],"classname":"displacement"},{"index":4,"clusters":[1033,1035],"classname":"displacement"},{"index":5,"clusters":[1033],"classname":"displacement"},{"index":6,"clusters":[1033,1035],"classname":"displacement"},{"index":7,"clusters":[1033,1035],"classname":"displacement"},{"index":8,"clusters":[1033,1035],"classname":"displacement"},{"index":9,"clusters":[1033],"classname":"displacement"},{"index":10,"clusters":[1045],"classname":"displacement"},{"index":11,"clusters":[1044,1045],"classname":"displacement"},{"index":12,"clusters":[1044,1045],"classname":"displacement"},{"index":13,"clusters":[1044],"classname":"displacement"},{"index":14,"clusters":[1044,1045],"classname":"displacement"},{"index":15,"clusters":[1044,1045],"classname":"displacement"},{"index":16,"clusters":[1044,1045],"classname":"displacement"},{"index":17,"clusters":[1044,1045],"classname":"displacement"},{"index":18,"clusters":[1044],"classname":"displacement"},{"index":19,"clusters":[1044],"classname":"displacement"},{"index":20,"clusters":[1035],"classname":"displacement"},{"index":21,"clusters":[1035,1036],"classname":"displacement"},{"index":22,"clusters":[1035,1036],"classname":"displacement"},{"index":23,"clusters":[1036],"classname":"displacement"},{"index":24,"clusters":[1035,1036],"classname":"displacement"},{"index":25,"clusters":[1035],"classname":"displacement"},{"index":26,"clusters":[1035,1036],"classname":"displacement"},{"index":27,"clusters":[1035,1036],"classname":"displacement"},{"index":28,"clusters":[1035,1036],"classname":"displacement"},{"index":29,"clusters":[1035],"classname":"displacement"},{"index":30,"clusters":[1038],"classname":"displacement"},{"index":31,"clusters":[1038],"classname":"displacement"},{"index":32,"clusters":[1038],"classname":"displacement"},{"index":33,"clusters":[1038],"classname":"displacement"},{"index":34,"clusters":[1038],"classname":"displacement"},{"index":35,"clusters":[1038],"classname":"displacement"},{"index":36,"clusters":[1038],"classname":"displacement"},{"index":37,"clusters":[1038],"classname":"displacement"},{"index":38,"clusters":[1038],"classname":"displacement"},{"index":39,"clusters":[1038],"classname":"displacement"},{"index":40,"clusters":[2930,2933,2948,2950,2951],"classname":"displacement"},{"index":41,"clusters":[2930,2933],"classname":"displacement"},{"index":42,"clusters":[2933,2951,3039,3066],"classname":"displacement"},{"index":43,"clusters":[2950,2951,2954,2955,2956],"classname":"displacement"},{"index":44,"clusters":[2930,2933,2948,2950,2951],"classname":"displacement"},{"index":45,"clusters":[2933,2951,3039,3066],"classname":"displacement"},{"index":46,"clusters":[2950,2951,2954,2955,2956],"classname":"displacement"},{"index":47,"clusters":[2951],"classname":"displacement"},{"index":48,"clusters":[2930,2933,2948,2950,2951],"classname":"displacement"},{"index":49,"clusters":[2930,2933,2948,2951],"classname":"displacement"},{"index":50,"clusters":[3070,3076],"classname":"displacement"},{"index":51,"clusters":[3070,3082,3083,3085,3086,3090],"classname":"displacement"},{"index":52,"clusters":[3085,3086,3090,3102,3104],"classname":"displacement"},{"index":53,"clusters":[3076,3098,3101,3102,3104],"classname":"displacement"},{"index":54,"clusters":[3070,3086,3090],"classname":"displacement"},{"index":55,"clusters":[3086,3090,3100,3101,3102,3104],"classname":"displacement"},{"index":56,"clusters":[3086,3100],"classname":"displacement"},{"index":57,"clusters":[3076,3098,3100,3101,3102,3104],"classname":"displacement"},{"index":58,"clusters":[3070,3076,3086,3098,3100,3101],"classname":"displacement"},{"index":59,"clusters":[3070,3076,3082,3083,3084,3085,3090,3098,3099,3101,3102,3104],"classname":"displacement"},{"index":60,"clusters":[3302],"classname":"displacement"},{"index":61,"clusters":[3302],"classname":"displacement"},{"index":62,"clusters":[3302],"classname":"displacement"},{"index":63,"clusters":[3302],"classname":"displacement"},{"index":64,"clusters":[3302],"classname":"displacement"},{"index":65,"clusters":[3302],"classname":"displacement"},{"index":66,"clusters":[3302],"classname":"displacement"},{"index":67,"clusters":[3302],"classname":"displacement"},{"index":68,"clusters":[3302],"classname":"displacement"},{"index":69,"clusters":[3302],"classname":"displacement"},{"index":70,"clusters":[3053],"classname":"displacement"},{"index":71,"clusters":[3053],"classname":"displacement"},{"index":72,"clusters":[3053],"classname":"displacement"},{"index":73,"clusters":[3053],"classname":"displacement"},{"index":74,"clusters":[3053],"classname":"displacement"},{"index":75,"clusters":[3053],"classname":"displacement"},{"index":76,"clusters":[3053],"classname":"displacement"},{"index":77,"clusters":[3053],"classname":"displacement"},{"index":78,"clusters":[3053],"classname":"displacement"},{"index":79,"clusters":[3053],"classname":"displacement"},{"index":80,"clusters":[3036],"classname":"displacement"},{"index":81,"clusters":[3036],"classname":"displacement"},{"index":82,"clusters":[3036],"classname":"displacement"},{"index":83,"clusters":[3032,3036],"classname":"displacement"},{"index":84,"clusters":[3032,3036],"classname":"displacement"},{"index":85,"clusters":[3036],"classname":"displacement"},{"index":86,"clusters":[3036],"classname":"displacement"},{"index":87,"clusters":[3036],"classname":"displacement"},{"index":88,"clusters":[3032,3036],"classname":"displacement"},{"index":89,"clusters":[3036],"classname":"displacement"},{"model":0,"vertLighting":0,"flags":16,"clusters":[2220,2213,2186,2172],"classname":"prop_static","origin":{"x":1640.0,"y":-4483.0,"z":11778.0},"angles":{"x":0.0,"y":0.0,"z":0.0},"scale":13.0},{"model":0,"vertLighting":1,"flags":16,"clusters":[2228,2220,2216,2213],"classname":"prop_static","origin":{"x":1629.0,"y":-5121.0,"z":11778.0},"angles":{"x":0.0,"y":300.0,"z":0.0},"scale":13.0},{"model":0,"vertLighting":2,"flags":16,"clusters":[2888,2883,2880,2876],"classname":"prop_static","origin":{"x":-3042.0,"y":-5084.0,"z":11778.0},"angles":{"x":0.0,"y":300.0,"z":0.0},"scale":13.0},{"model":0,"vertLighting":3,"flags":16,"clusters":[2880,2876,2801,2796],"classname":"prop_static","origin":{"x":-3031.0,"y":-4446.0,"z":11778.0},"angles":{"x":0.0,"y":0.0,"z":0.0},"scale":13.0},{"model":0,"vertLighting":4,"flags":16,"clusters":[2953,2949,2936,2935,2932,2931],"classname":"prop_static","origin":{"x":-6944.0,"y":-6265.0,"z":-9934.0},"angles":{"x":0.0,"y":87.412,"z":0.0},"scale":13.0},{"model":0,"vertLighting":5,"flags":16,"clusters":[3163,3158,3157,3092,3065,3064],"classname":"prop_static","origin":{"x":-12487.0,"y":-6198.0,"z":-9934.0},"angles":{"x":0.0,"y":357.412,"z":0.0},"scale":13.0}]}